Workbook

Sheet Pivot
A3: Row Labels | B3: Count of Kind
B4: 316
A5: BID | B5: 437
A6: BID+DEAL+NEXT | B6: 1
A7: BID+NEXT | B7: 124
A8: BID+NEXT+ROTATE | B8: 75
A9: NEXT | B9: 220
A10: Grand Total | B10: 1173

Sheet BakerBridge
A1: Subfolder | B1: Filename | C1: DealNumber | D1: B1 | E1: Kind | F1: North | G1: East | H1: South | I1: West | J1: B2 | K1: Hands | L1: B2 | M1: BC Import | R1: Dealer | S1: Auction | T1: Contract | U1: Declarer | V1: Lead | W1: Analysis
A2: ='CSV Import'!A2 -> 100Deals | B2: ='CSV Import'!B2 -> deal001.html | C2: ='CSV Import'!C2 -> 1 | E2: =IF('CSV Import'!D2="","",'CSV Import'!D2) -> BID+NEXT | F2: =IF('CSV Import'!E2="","",'CSV Import'!E2) -> S:J86 H:A98 D:8653 C:AKQ | G2: =IF('CSV Import'!F2="","",'CSV Import'!F2) -> S:A9 H:QT54 D:QJT2 C:JT3 | H2: =IF('CSV Import'!G2="","",'CSV Import'!G2) -> S:Q53 H:762 D:AK4 C:8742 | I2: =IF('CSV Import'!H2="","",'CSV Import'!H2) -> S:KT742 H:KJ3 D:97 C:965 | K2: =4-COUNTIF(F2:I2,"") -> 4 | M2: =SUBSTITUTE(SUBSTITUTE(SUBSTITUTE(SUBSTITUTE(F2,"S:","")," H:",".")," D:",".")," C:",".") -> J86.A98.8653.AKQ | N2: =SUBSTITUTE(SUBSTITUTE(SUBSTITUTE(SUBSTITUTE(G2,"S:","")," H:",".")," D:",".")," C:",".") -> A9.QT54.QJT2.JT3 | O2: =SUBSTITUTE(SUBSTITUTE(SUBSTITUTE(SUBSTITUTE(H2,"S:","")," H:",".")," D:",".")," C:",".") -> Q53.762.AK4.8742 | P2: =SUBSTITUTE(SUBSTITUTE(SUBSTITUTE(SUBSTITUTE(I2,"S:","")," H:",".")," D:",".")," C:",".") -> KT742.KJ3.97.965 | R2: =IF('CSV Import'!I2="","",'CSV Import'!I2) -> North | S2: =IF('CSV Import'!J2="","",'CSV Import'!J2) -> 1D pass 1NT | pass pass pass | T2: =IF('CSV Import'!K2="","",'CSV Import'!K2) -> 1NT | U2: =IF('CSV Import'!L2="","",'CSV Import'!L2) -> South | V2: =IF('CSV Import'!M2="","",'CSV Import'!M2) -> S4 | W2: =IF('CSV Import'!N2="","",'CSV Import'!N2) -> You are South and it is your bid. Decide what you would say, then click on BID. [BID 1NT]\nDo not be tempted to say 2!D, even with such good 3-card help. To support partner's minor suit opening you should have at least 4 cards in the suit. Remember he may have opened a 3-card suit.\nInstead you bid 1NT showing a balanced 6-10 point hand with no 4-card Major suit. Partner passes.\nSouth plays 1NT. West leads the !S4. East wins the !SA, then plays the !S9. West takes his !SK and leads another !S, East discarding a !H.\nMake a Plan, then click NEXT. [NEXT]\nTo make a PLAN for a Notrump contract you should count your winners.\nWinners: !S 1 : !H 1 : !D 2 : !C 3 : Total = 7\nFor this deal you see that you already have all the winners you need to make the contract. So you just want to be sure you don't do something stupid that would jeopardize those winners.\nYou win the !SQ, then lead to the !CA, !CK, !CQ. Everybody follows suit to these three tricks. Next you take the !HA. Then you play a small !D to your !DK, then play your !DA. You have now won your required 7 tricks, but you have a bonus. Since all the !Cs except the !C8 have been played your !C8 is now high and you make an overtrick.\nClick NEXT to see the complete deal. [NEXT]\nBut even with this type of hand you should make sure you take them in the right order. Here, if you had played the !DA and !DK BEFORE you played the !C A K Q you would have had no entry back to the fourth !C in your hand. In this case it was only an overtrick, in other deals it could make the difference between making and going down.
A3: ='CSV Import'!A3 -> 100Deals | B3: ='CSV Import'!B3 -> deal002.html | C3: ='CSV Import'!C3 -> 2 | E3: =IF('CSV Import'!D3="","",'CSV Import'!D3) -> BID+NEXT | F3: =IF('CSV Import'!E3="","",'CSV Import'!E3) -> S:74 H:KQJ3 D:AK75 C:863 | G3: =IF('CSV Import'!F3="","",'CSV Import'!F3) -> S:J986 H:A5 D:Q32 C:QJT4 | H3: =IF('CSV Import'!G3="","",'CSV Import'!G3) -> S:AKQ3 H:T982 D:J4 C:K72 | I3: =IF('CSV Import'!H3="","",'CSV Import'!H3) -> S:T52 H:764 D:T986 C:A95 | K3: =4-COUNTIF(F3:I3,"") -> 4 | M3: =SUBSTITUTE(SUBSTITUTE(SUBSTITUTE(SUBSTITUTE(F3,"S:","")," H:",".")," D:",".")," C:",".") -> 74.KQJ3.AK75.863 | N3: =SUBSTITUTE(SUBSTITUTE(SUBSTITUTE(SUBSTITUTE(G3,"S:","")," H:",".")," D:",".")," C:",".") -> J986.A5.Q32.QJT4 | O3: =SUBSTITUTE(SUBSTITUTE(SUBSTITUTE(SUBSTITUTE(H3,"S:","")," H:",".")," D:",".")," C:",".") -> AKQ3.T982.J4.K72 | P3: =SUBSTITUTE(SUBSTITUTE(SUBSTITUTE(SUBSTITUTE(I3,"S:","")," H:",".")," D:",".")," C:",".") -> T52.764.T986.A95 | R3: =IF('CSV Import'!I3="","",'CSV Import'!I3) -> North | S3: =IF('CSV Import'!J3="","",'CSV Import'!J3) -> 1D pass 1H | pass 2H pass 4H | pass pass pass | T3: =IF('CSV Import'!K3="","",'CSV Import'!K3) -> 4H | U3: =IF('CSV Import'!L3="","",'CSV Import'!L3) -> South | V3: =IF('CSV Import'!M3="","",'CSV Import'!M3) -> DT | W3: =IF('CSV Import'!N3="","",'CSV Import'!N3) -> You are South and it is your bid. Decide what you would say, then click on BID. [BID 1!H]\nA jump to 2NT would be descriptive, but your first goal is to seek a Major suit fit. When you have two 4-card Majors you should respond "up-the-line" so you bid 1!H. Partner says 2!H. What do you bid now? [BID 4!H]\nPartner would not support your !H suit without 4 cards so you have an 8-card Major fit. There is no point in bidding !Ss.\nPartner has at least 13 points and you have 13 so you bid the game.\nSouth plays 4!H. West leads the !DT.\nMake a Plan, then click NEXT. [NEXT]\nTo make a PLAN for a suit contract you should count your losers.\nLosers: !S 0 : !H 1 : !D 0 : !C 3 : Total = 4\nThere is nothing you can do about losing the Ace of trumps. The three !C losers would only happen if West has the !CA and East wins a trick early, (say with the !HA), and leads a !C through your !CK.\nYou can take care of this possibility by discarding a !C from dummy BEFORE you play trumps. So win the !DK, and play !SA, !SK, !SQ, discarding dummy's !C3 on the last one. Then pull trumps. You will end up losing two !Cs and the !HA.\nClick NEXT to see the Deal that could have set you. [NEXT]\nEast would win his !HA and would switch to a black suit to lead up to dummy's weakness. In this case he would surely lead the !CQ, and you would lose three !C tricks and be down before you started.\nMaking a PLAN is a necessary part of being a good Declarer and Visualizing what might happen is a necessary part of making a Plan.
A4: ='CSV Import'!A4 -> 100Deals | B4: ='CSV Import'!B4 -> deal003.html | C4: ='CSV Import'!C4 -> 3 | E4: =IF('CSV Import'!D4="","",'CSV Import'!D4) -> BID+NEXT | F4: =IF('CSV Import'!E4="","",'CSV Import'!E4) -> S:AQ5 H:74 D:Q962 C:AJT8 | G4: =IF('CSV Import'!F4="","",'CSV Import'!F4) -> S:KT H:QJT982 D:83 C:652 | H4: =IF('CSV Import'!G4="","",'CSV Import'!G4) -> S:872 H:K6 D:AKJ4 C:KQ74 | I4: =IF('CSV Import'!H4="","",'CSV Import'!H4) -> S:J9643 H:A53 D:T75 C:93 | K4: =4-COUNTIF(F4:I4,"") -> 4 | M4: =SUBSTITUTE(SUBSTITUTE(SUBSTITUTE(SUBSTITUTE(F4,"S:","")," H:",".")," D:",".")," C:",".") -> AQ5.74.Q962.AJT8 | N4: =SUBSTITUTE(SUBSTITUTE(SUBSTITUTE(SUBSTITUTE(G4,"S:","")," H:",".")," D:",".")," C:",".") -> KT.QJT982.83.652 | O4: =SUBSTITUTE(SUBSTITUTE(SUBSTITUTE(SUBSTITUTE(H4,"S:","")," H:",".")," D:",".")," C:",".") -> 872.K6.AKJ4.KQ74 | P4: =SUBSTITUTE(SUBSTITUTE(SUBSTITUTE(SUBSTITUTE(I4,"S:","")," H:",".")," D:",".")," C:",".") -> J9643.A53.T75.93 | R4: =IF('CSV Import'!I4="","",'CSV Import'!I4) -> East | S4: =IF('CSV Import'!J4="","",'CSV Import'!J4) -> pass 1NT | pass 3NT pass pass | pass | T4: =IF('CSV Import'!K4="","",'CSV Import'!K4) -> 3NT | U4: =IF('CSV Import'!L4="","",'CSV Import'!L4) -> South | V4: =IF('CSV Import'!M4="","",'CSV Import'!M4) -> S4 | W4: =IF('CSV Import'!N4="","",'CSV Import'!N4) -> You are South and it is your bid. Decide what you would say, then click on BID. [BID 1NT]\nWith 16 points and a balanced hand you should open 1NT. Do not worry about the lack of a !S stopper, a 1NT opening does not guarantee stoppers in all four suits.\nPartner raises you to 3NT.\nSouth plays 3NT. West leads the !S4.\nMake a Plan, then click NEXT. [NEXT]\nWinners: !S 1 : !H 0 : !D 4 : !C 4 : Total = 9\nIt's nice to have a hand where the Winner count is 9. And guess what? West probably has the !SK, so you can finesse on the first trick for an overtrick.\nHOLD IT! JUST STEP AWAY FROM THE QUEEN OF SPADES AND NOBODY WILL GET HURT.\nWhat if you tried the finesse and East had the !SK? And what if he then switched to the !HQ? And what if your opponents then took the next 6 !H tricks? \nI think you get the idea. Win the !SA immediately and then take your other 8 tricks.\nClick NEXT to see the complete Deal. [NEXT]\nThis wasn't one of those times.
A5: ='CSV Import'!A5 -> 100Deals | B5: ='CSV Import'!B5 -> deal004.html | C5: ='CSV Import'!C5 -> 4 | E5: =IF('CSV Import'!D5="","",'CSV Import'!D5) -> BID+NEXT | F5: =IF('CSV Import'!E5="","",'CSV Import'!E5) -> S:KQJ H:A862 D:Q63 C:T94 | G5: =IF('CSV Import'!F5="","",'CSV Import'!F5) -> S:72 H:QT43 D:AJ92 C:Q73 | H5: =IF('CSV Import'!G5="","",'CSV Import'!G5) -> S:T98653 H:K7 D:84 C:AKJ | I5: =IF('CSV Import'!H5="","",'CSV Import'!H5) -> S:A4 H:J95 D:KT75 C:8652 | K5: =4-COUNTIF(F5:I5,"") -> 4 | M5: =SUBSTITUTE(SUBSTITUTE(SUBSTITUTE(SUBSTITUTE(F5,"S:","")," H:",".")," D:",".")," C:",".") -> KQJ.A862.Q63.T94 | N5: =SUBSTITUTE(SUBSTITUTE(SUBSTITUTE(SUBSTITUTE(G5,"S:","")," H:",".")," D:",".")," C:",".") -> 72.QT43.AJ92.Q73 | O5: =SUBSTITUTE(SUBSTITUTE(SUBSTITUTE(SUBSTITUTE(H5,"S:","")," H:",".")," D:",".")," C:",".") -> T98653.K7.84.AKJ | P5: =SUBSTITUTE(SUBSTITUTE(SUBSTITUTE(SUBSTITUTE(I5,"S:","")," H:",".")," D:",".")," C:",".") -> A4.J95.KT75.8652 | R5: =IF('CSV Import'!I5="","",'CSV Import'!I5) -> South | S5: =IF('CSV Import'!J5="","",'CSV Import'!J5) -> 1S | pass 2H pass 2S | pass 4S pass pass | pass | T5: =IF('CSV Import'!K5="","",'CSV Import'!K5) -> 4S | U5: =IF('CSV Import'!L5="","",'CSV Import'!L5) -> South | V5: =IF('CSV Import'!M5="","",'CSV Import'!M5) -> D5 | W5: =IF('CSV Import'!N5="","",'CSV Import'!N5) -> You are South and it is your bid. Decide what you would say, then click on BID. [BID 1!S]\nDon't think of passing. With 11 HCP and 2 length points you open 1!S. Partner responds 2!H. What is your next bid? [BID 2!S]\nYou must bid and you want to show that you have a bare minimum. You don't want to say 2NT because of that doubleton nothing !D. So you rebid your 6-card !S suit. Partner bids 4!S and everybody passes.\nSouth plays 4!S. West leads the !D5 on which you play dummy's !D3. East wins !DJ, plays !DA, then !D2.\nMake a Plan, then click NEXT. [NEXT]\nLosers: !S 1 : !H 0 : !D 2 : !C 1 : Total = 4\nYou have already lost the 2 !Ds and you sure can't escape losing the Ace of trumps. So you mustnot lose a !C trick. So your Plan will be to pull trumps, then finesse East for the !CQ. \nYou ruff the third !D, play !Ss until the !SA appears. When you regain the lead you pull any outstanding trumps, play one high !C, (in case someone has a singleton !CQ), then enter dummy with the !HA and make the !C finesse. Half of the time you make the contract, the other half you don't.\nClick NEXT to see the full deal. [NEXT]\nIt's never great when the success of your contract depends on a finesse, but sometimes that's your only hope - a 50% chance.
A6: ='CSV Import'!A6 -> 100Deals | B6: ='CSV Import'!B6 -> deal005.html | C6: ='CSV Import'!C6 -> 5 | E6: =IF('CSV Import'!D6="","",'CSV Import'!D6) -> BID+NEXT | F6: =IF('CSV Import'!E6="","",'CSV Import'!E6) -> S:J64 H:Q7 D:A983 C:KQ76 | G6: =IF('CSV Import'!F6="","",'CSV Import'!F6) -> S:A7 H:K653 D:762 C:T543 | H6: =IF('CSV Import'!G6="","",'CSV Import'!G6) -> S:KQT3 H:A4 D:QJT5 C:AJ2 | I6: =IF('CSV Import'!H6="","",'CSV Import'!H6) -> S:9852 H:JT982 D:K4 C:98 | K6: =4-COUNTIF(F6:I6,"") -> 4 | M6: =SUBSTITUTE(SUBSTITUTE(SUBSTITUTE(SUBSTITUTE(F6,"S:","")," H:",".")," D:",".")," C:",".") -> J64.Q7.A983.KQ76 | N6: =SUBSTITUTE(SUBSTITUTE(SUBSTITUTE(SUBSTITUTE(G6,"S:","")," H:",".")," D:",".")," C:",".") -> A7.K653.762.T543 | O6: =SUBSTITUTE(SUBSTITUTE(SUBSTITUTE(SUBSTITUTE(H6,"S:","")," H:",".")," D:",".")," C:",".") -> KQT3.A4.QJT5.AJ2 | P6: =SUBSTITUTE(SUBSTITUTE(SUBSTITUTE(SUBSTITUTE(I6,"S:","")," H:",".")," D:",".")," C:",".") -> 9852.JT982.K4.98 | R6: =IF('CSV Import'!I6="","",'CSV Import'!I6) -> East | S6: =IF('CSV Import'!J6="","",'CSV Import'!J6) -> pass 1NT | pass 3NT pass pass | pass | T6: =IF('CSV Import'!K6="","",'CSV Import'!K6) -> 3NT | U6: =IF('CSV Import'!L6="","",'CSV Import'!L6) -> South | V6: =IF('CSV Import'!M6="","",'CSV Import'!M6) -> HJ | W6: =IF('CSV Import'!N6="","",'CSV Import'!N6) -> You are South and it is your bid. Decide what you would say, then click on BID. [BID 1NT]\nYou have a very solid 17 points and a balanced hand. You open 1NT. Partner responds 3NT and you pass.\nSouth plays 3NT. West leads the !HJ. You hopefully put on the !HQ, but East plays the !HK.\nMake a Plan, then click NEXT. [NEXT]\nYou hopefully put on the !HQ, but East plays the !HK.\nWinners: !S 0 : !H 1 : !D 1 : !C 4 : Total = 6\nA hold-up won't help unless East had a doubleton !H, giving West a 7-card suit. So you win your !HA. The !S suit is solid after the !SA is played, but before you could enjoy those 3 tricks the defenders would have really enjoyed a bunch of !Hs.\nYour only hope is to win 8 more tricks before you lose the lead. That means the !D finesse had better work. At trick 2 you lead your !DQ, playing low from dummy if West doesn't cover. Repeat the finesse as necessary. When West has the !DK you will make your contract, and when East has the !DK you will go down. That's a 50% chance, just like most finesses. But remember, if you had tried to establish the !S suit instead of taking the finesse your chance of making 3NT would be 0%.\nClick for the full deal. [NEXT]\n
A7: ='CSV Import'!A7 -> 100Deals | B7: ='CSV Import'!B7 -> deal006.html | C7: ='CSV Import'!C7 -> 6 | E7: =IF('CSV Import'!D7="","",'CSV Import'!D7) -> BID+NEXT+ROTATE | F7: =IF('CSV Import'!E7="","",'CSV Import'!E7) -> S:QJT9 H:A5 D:7542 C:973 | G7: =IF('CSV Import'!F7="","",'CSV Import'!F7) -> S:K63 H:QJT83 D:J C:KJ62 | H7: =IF('CSV Import'!G7="","",'CSV Import'!G7) -> S:A2 H:K742 D:A863 C:AT5 | I7: =IF('CSV Import'!H7="","",'CSV Import'!H7) -> S:8754 H:96 D:KQT9 C:Q84 | K7: =4-COUNTIF(F7:I7,"") -> 4 | M7: =SUBSTITUTE(SUBSTITUTE(SUBSTITUTE(SUBSTITUTE(F7,"S:","")," H:",".")," D:",".")," C:",".") -> QJT9.A5.7542.973 | N7: =SUBSTITUTE(SUBSTITUTE(SUBSTITUTE(SUBSTITUTE(G7,"S:","")," H:",".")," D:",".")," C:",".") -> K63.QJT83.J.KJ62 | O7: =SUBSTITUTE(SUBSTITUTE(SUBSTITUTE(SUBSTITUTE(H7,"S:","")," H:",".")," D:",".")," C:",".") -> A2.K742.A863.AT5 | P7: =SUBSTITUTE(SUBSTITUTE(SUBSTITUTE(SUBSTITUTE(I7,"S:","")," H:",".")," D:",".")," C:",".") -> 8754.96.KQT9.Q84 | R7: =IF('CSV Import'!I7="","",'CSV Import'!I7) -> North | S7: =IF('CSV Import'!J7="","",'CSV Import'!J7) -> 1NT | pass pass pass | | T7: =IF('CSV Import'!K7="","",'CSV Import'!K7) -> 1NT | U7: =IF('CSV Import'!L7="","",'CSV Import'!L7) -> North | V7: =IF('CSV Import'!M7="","",'CSV Import'!M7) -> HQ | W7: =IF('CSV Import'!N7="","",'CSV Import'!N7) -> You are South and it is your bid. Decide what you would say, then click on BID. [BID pass]\nYou have 7 points so you know your side does not have a game. You also have no reason to think there is any better contract than 1NT. So you pass.\nNorth would play 1NT. To make life more convenient the hands will be rotated so that South becomes declarer. \nClick ROTATE. [ROTATE]\nSouth plays 1NT. West leads the !HQ.\nMake a Plan, then click NEXT. [NEXT]\nWinners: !S 1 : !H 2 : !D 1 : !C 1 : Total = 5\nYou need two more winners. Even if the !Ds split 3-2 you can get only one more from that suit. So clearly you must use the !S suit. Since you have only one entry to dummy you must save it until the right time.\nWin the first trick with the !HK. Then play !SA followed by !S2. Continue playing !Ss until the !SK is forced out. Win whatever they play next and play your other winners. You cannot be stopped from taking 7 tricks.\nClick NEXT to see the full deal. [NEXT]\nWhat would you try next? A !S finesse? Whether West took his !SK right then or later you would go down. You could never reach dummy again.
A8: ='CSV Import'!A8 -> 100Deals | B8: ='CSV Import'!B8 -> deal007.html | C8: ='CSV Import'!C8 -> 7 | E8: =IF('CSV Import'!D8="","",'CSV Import'!D8) -> BID+NEXT | F8: =IF('CSV Import'!E8="","",'CSV Import'!E8) -> S:T64 H:KJ7 D:86 C:J7532 | G8: =IF('CSV Import'!F8="","",'CSV Import'!F8) -> S:982 H:5 D:QT742 C:AK96 | H8: =IF('CSV Import'!G8="","",'CSV Import'!G8) -> S:QJ5 H:AQT963 D:AK5 C:Q | I8: =IF('CSV Import'!H8="","",'CSV Import'!H8) -> S:AK73 H:842 D:J93 C:T84 | K8: =4-COUNTIF(F8:I8,"") -> 4 | M8: =SUBSTITUTE(SUBSTITUTE(SUBSTITUTE(SUBSTITUTE(F8,"S:","")," H:",".")," D:",".")," C:",".") -> T64.KJ7.86.J7532 | N8: =SUBSTITUTE(SUBSTITUTE(SUBSTITUTE(SUBSTITUTE(G8,"S:","")," H:",".")," D:",".")," C:",".") -> 982.5.QT742.AK96 | O8: =SUBSTITUTE(SUBSTITUTE(SUBSTITUTE(SUBSTITUTE(H8,"S:","")," H:",".")," D:",".")," C:",".") -> QJ5.AQT963.AK5.Q | P8: =SUBSTITUTE(SUBSTITUTE(SUBSTITUTE(SUBSTITUTE(I8,"S:","")," H:",".")," D:",".")," C:",".") -> AK73.842.J93.T84 | R8: =IF('CSV Import'!I8="","",'CSV Import'!I8) -> South | S8: =IF('CSV Import'!J8="","",'CSV Import'!J8) -> 1H | pass 2H pass 4H | pass pass pass | | T8: =IF('CSV Import'!K8="","",'CSV Import'!K8) -> 4H | U8: =IF('CSV Import'!L8="","",'CSV Import'!L8) -> South | V8: =IF('CSV Import'!M8="","",'CSV Import'!M8) -> SA | W8: =IF('CSV Import'!N8="","",'CSV Import'!N8) -> You are South and it is your bid. Decide what you would say, then click on BID. [BID 4!H]\nYou have a nice hand, but 20 points is not strong enough to open 2!C. \nSo you open 1!H. Partner raises to 2!H. What do you bid now? [BID pass]\nPartner's raise to 2!H shows 6-10 points. You figure that should be enough for game but even if he has the full T you are not in slam range. So you bid the game. \nSouth plays 4!H. West leads !SA, then switches to !H2.\nMake a Plan, then click NEXT. [NEXT]\nLosers: !S 2 : !H 0 : !D 1 : !C 1 : Total = 4\nIt's a good thing you stopped at game - partner's hand is about as bad as it could be.\nThe PLAN turns out simple. You can't avoid either of the three black losers so you must eliminate the !D loser. You can ruff it in dummy. Just to be safe you pull one more round of trumps, then play !DA, !DK and !D5, ruffing in dummy. You will eventually get to your hand (with a !S or a !C ruff) and pull the last trump.\nClick NEXT to see the full deal. [NEXT]\nOnly a real beginner would have pulled all the trumps and not been able to ruff that !D.
A9: ='CSV Import'!A9 -> 100Deals | B9: ='CSV Import'!B9 -> deal008.html | C9: ='CSV Import'!C9 -> 8 | E9: =IF('CSV Import'!D9="","",'CSV Import'!D9) -> BID+NEXT+ROTATE | F9: =IF('CSV Import'!E9="","",'CSV Import'!E9) -> S:74 H:K53 D:AK962 C:KQ3 | G9: =IF('CSV Import'!F9="","",'CSV Import'!F9) -> S:QJT82 H:T86 D:754 C:A5 | H9: =IF('CSV Import'!G9="","",'CSV Import'!G9) -> S:A9 H:AJ2 D:QJ3 C:JT862 | I9: =IF('CSV Import'!H9="","",'CSV Import'!H9) -> S:K653 H:Q974 D:T8 C:974 | K9: =4-COUNTIF(F9:I9,"") -> 4 | M9: =SUBSTITUTE(SUBSTITUTE(SUBSTITUTE(SUBSTITUTE(F9,"S:","")," H:",".")," D:",".")," C:",".") -> 74.K53.AK962.KQ3 | N9: =SUBSTITUTE(SUBSTITUTE(SUBSTITUTE(SUBSTITUTE(G9,"S:","")," H:",".")," D:",".")," C:",".") -> QJT82.T86.754.A5 | O9: =SUBSTITUTE(SUBSTITUTE(SUBSTITUTE(SUBSTITUTE(H9,"S:","")," H:",".")," D:",".")," C:",".") -> A9.AJ2.QJ3.JT862 | P9: =SUBSTITUTE(SUBSTITUTE(SUBSTITUTE(SUBSTITUTE(I9,"S:","")," H:",".")," D:",".")," C:",".") -> K653.Q974.T8.974 | R9: =IF('CSV Import'!I9="","",'CSV Import'!I9) -> West | S9: =IF('CSV Import'!J9="","",'CSV Import'!J9) -> pass 1C | pass 1D pass 1NT | pass 3NT pass pass | pass | T9: =IF('CSV Import'!K9="","",'CSV Import'!K9) -> 3NT | U9: =IF('CSV Import'!L9="","",'CSV Import'!L9) -> North | V9: =IF('CSV Import'!M9="","",'CSV Import'!M9) -> SQ | W9: =IF('CSV Import'!N9="","",'CSV Import'!N9) -> You are South and it is your bid. Decide what you would say, then click on BID. [BID pass]\nWith 16 points as Responder you are not quite strong enough for a jump-shift to 2 !D. That requires at least 17 points. A jump to 3NT fits the point range (16-18) but promises a stopper in all unbid suits. So instead you bid 1!D, knowing partner is forced to keep the bidding alive. He now replies 1NT. What is your next bid? [BID pass]\nUntil now you were thinking the hand might end up in a slam. Now, with partner's minimum rebid, you happily say 3NT which partner passes.\nNorth would play 3NT. \nClick [ROTATE]\nSouth plays 3NT. West leads the !SQ. East puts on the !SK.\nMake a Plan, then click NEXT. [NEXT]\nWinners: !S 1 : !H 2 : !D 5 : !C 0 : Total = 8\nLet's say you hold up on the first !S, hoping they switch suits. HA! They aren't about to switch suits and they drive out your !SA at trick 2. That actually clears the situation up and makes this plan pretty simple to make.\nYou have taken 1 !S, and you will surely make 5 !Ds. Despite the solidity of those !Cs you dare not try to win a !C trick, because the defenders will pounce on that first !C and then win a bunch of !S tricks. \nSo that makes it clear that you need 3 !H tricks, and there's only one way to get them. After taking your five !D tricks, play a !H to the !HK, then a !H back, finessing the !HJ. Half of the time you will make this contract, the other half of the time they will bury you with !Ss.\nClick NEXT to see the full deal. [NEXT]\n
A10: ='CSV Import'!A10 -> 100Deals | B10: ='CSV Import'!B10 -> deal009.html | C10: ='CSV Import'!C10 -> 9 | E10: =IF('CSV Import'!D10="","",'CSV Import'!D10) -> BID+NEXT+ROTATE | F10: =IF('CSV Import'!E10="","",'CSV Import'!E10) -> S:952 H:KQ92 D:KQ83 C:J7 | G10: =IF('CSV Import'!F10="","",'CSV Import'!F10) -> S:KQJ8 H: D:9764 C:QT652 | H10: =IF('CSV Import'!G10="","",'CSV Import'!G10) -> S:T63 H:AT754 D:AJ2 C:AK | I10: =IF('CSV Import'!H10="","",'CSV Import'!H10) -> S:A74 H:J863 D:T5 C:9843 | K10: =4-COUNTIF(F10:I10,"") -> 4 | M10: =SUBSTITUTE(SUBSTITUTE(SUBSTITUTE(SUBSTITUTE(F10,"S:","")," H:",".")," D:",".")," C:",".") -> 952.KQ92.KQ83.J7 | N10: =SUBSTITUTE(SUBSTITUTE(SUBSTITUTE(SUBSTITUTE(G10,"S:","")," H:",".")," D:",".")," C:",".") -> KQJ8..9764.QT652 | O10: =SUBSTITUTE(SUBSTITUTE(SUBSTITUTE(SUBSTITUTE(H10,"S:","")," H:",".")," D:",".")," C:",".") -> T63.AT754.AJ2.AK | P10: =SUBSTITUTE(SUBSTITUTE(SUBSTITUTE(SUBSTITUTE(I10,"S:","")," H:",".")," D:",".")," C:",".") -> A74.J863.T5.9843 | R10: =IF('CSV Import'!I10="","",'CSV Import'!I10) -> North | S10: =IF('CSV Import'!J10="","",'CSV Import'!J10) -> 1H | pass 3H pass 4H | pass pass pass | T10: =IF('CSV Import'!K10="","",'CSV Import'!K10) -> 4H | U10: =IF('CSV Import'!L10="","",'CSV Import'!L10) -> North | V10: =IF('CSV Import'!M10="","",'CSV Import'!M10) | W10: =IF('CSV Import'!N10="","",'CSV Import'!N10) -> You are South and it is your bid. Decide what you would say, then click on BID. [BID 3!H]\nYou have 12 points which isn't quite enough to force to game.\nIt is just right for a limit raise though, so you bid 3!H.\nPartner does bid the game.\nNorth would play 4!H.\nClick [ROTATE]\nSouth plays 4!H. The defense takes the first three !S tricks, then switches to a !C.\nMake a Plan, then click NEXT. [NEXT]\nLosers: !S 3 : !H ?? : !D 0 : !C 0 : Total = 3+??\nWith no more outside losers your task is very very simple:DO NOT LOSE A TRUMP TRICK.\nThere is no problem if trumps split 2-2 or 3-1, so you can put your mind to 4-0 splits only. If West holds !H J 8 6 3 then it won't matter whether your first trump play is !HA or !HK, you will still be able to finesse the !HJ. But if East holds !H J 8 6 3 it is vital that you first play either the !HK or !HQ. If you start with the !HA you will have lost your finesse position. The general rule is to first play a high trump from the hand that has two. That preserves a finesse through either defender's !H J x x x.\nClick NEXT to see the full deal. [NEXT]\nNext visualize the situation if your first play was the !HK. West would show out and you would play the !HQ, then a small !H finessing your !HT. \nFinally visualize the situation if your first play was the !HK and it was East who showed out. You would play a small !H to your !HA, then lead a !H toward dummy finessing with the !H9.\nUsing the correct Plan guarantees the contract however !Hs split.
A11: ='CSV Import'!A11 -> 100Deals | B11: ='CSV Import'!B11 -> deal010.html | C11: ='CSV Import'!C11 -> 10 | E11: =IF('CSV Import'!D11="","",'CSV Import'!D11) -> BID+NEXT | F11: =IF('CSV Import'!E11="","",'CSV Import'!E11) -> S:KQ92 H:952 D:K7 C:KQ83 | G11: =IF('CSV Import'!F11="","",'CSV Import'!F11) -> S: H:A874 D:QJ632 C:T764 | H11: =IF('CSV Import'!G11="","",'CSV Import'!G11) -> S:A8754 H:T63 D:A8 C:AJ2 | I11: =IF('CSV Import'!H11="","",'CSV Import'!H11) -> S:JT63 H:KQJ D:T954 C:95 | K11: =4-COUNTIF(F11:I11,"") -> 4 | M11: =SUBSTITUTE(SUBSTITUTE(SUBSTITUTE(SUBSTITUTE(F11,"S:","")," H:",".")," D:",".")," C:",".") -> KQ92.952.K7.KQ83 | N11: =SUBSTITUTE(SUBSTITUTE(SUBSTITUTE(SUBSTITUTE(G11,"S:","")," H:",".")," D:",".")," C:",".") -> .A874.QJ632.T764 | O11: =SUBSTITUTE(SUBSTITUTE(SUBSTITUTE(SUBSTITUTE(H11,"S:","")," H:",".")," D:",".")," C:",".") -> A8754.T63.A8.AJ2 | P11: =SUBSTITUTE(SUBSTITUTE(SUBSTITUTE(SUBSTITUTE(I11,"S:","")," H:",".")," D:",".")," C:",".") -> JT63.KQJ.T954.95 | R11: =IF('CSV Import'!I11="","",'CSV Import'!I11) -> North | S11: =IF('CSV Import'!J11="","",'CSV Import'!J11) -> 1C pass 1S | pass 2S pass 4S | pass pass pass | T11: =IF('CSV Import'!K11="","",'CSV Import'!K11) -> 4S | U11: =IF('CSV Import'!L11="","",'CSV Import'!L11) -> South | V11: =IF('CSV Import'!M11="","",'CSV Import'!M11) | W11: =IF('CSV Import'!N11="","",'CSV Import'!N11) -> You are South and it is your bid. Decide what you would say, then click on BID. [BID 1!S]\nPartner has opened and you have 14 points. You know you belong in game but there is no need to jump and use up bidding space. You respond 1!S.\nPartner now bids 2!S. What do you bid next? [BID 4!S]\nYou know you should be in game and now you know the suit. You bid 4!S.\nSouth plays 4!S. The defense quickly takes three !H tricks, then switches to a !D.\nMake a Plan, then click NEXT. [NEXT]\nLosers: !S 0? : !H 3 : !D 0 : !C 0 : Total = 3?\nThis Deal is VERY similar to Deal 9 in that you are only worried about a 4-0 trump split. The reason that it shows up right here is to point out the difference between J 8 6 3 and J T 6 3.\nIf East holds !S J T 6 3 then there is nothing you can do about it - you will go down. If you lead a !S from dummy he will "split his honors" by playing the !ST. This will force your !SA and he can just sit back and wait for his !SJ to make a trick.\nBut if it is West with !S J T 6 3 you can keep him from winning a !S trick, IF YOUR FIRST !S PLAY IS THE !SA. East shows out and you play a small !S toward dummy's !S K Q 9. If West plays low you insert the !S9, if he plays one of his honors you win it, then return to your hand and finesse him out of the other honor.\nClick NEXT to see the full deal. [NEXT]\nIf your first !S was !SK or !SQ then it would be too late.\nClick NEXT to see an alternate deal. [NEXT]\nTo summarize: If you are missing J x x x your first play should be from the hand with two honors. Then you will be able to finesse in either direction. If you are missing J T x x your first play should be honor from the hand with only one. This will leave you with a double-finesse position in one direction. If the other defender has the trumps there is nothing you can do.
A12: ='CSV Import'!A12 -> 100Deals | B12: ='CSV Import'!B12 -> deal011.html | C12: ='CSV Import'!C12 -> 11 | E12: =IF('CSV Import'!D12="","",'CSV Import'!D12) -> BID+NEXT | F12: =IF('CSV Import'!E12="","",'CSV Import'!E12) -> S:K82 H:754 D:K9542 C:Q3 | G12: =IF('CSV Import'!F12="","",'CSV Import'!F12) -> S:JT97 H:KQT6 D:J6 C:J54 | H12: =IF('CSV Import'!G12="","",'CSV Import'!G12) -> S:A63 H:A92 D:A87 C:A976 | I12: =IF('CSV Import'!H12="","",'CSV Import'!H12) -> S:Q54 H:J83 D:QT3 C:KT82 | K12: =4-COUNTIF(F12:I12,"") -> 4 | M12: =SUBSTITUTE(SUBSTITUTE(SUBSTITUTE(SUBSTITUTE(F12,"S:","")," H:",".")," D:",".")," C:",".") -> K82.754.K9542.Q3 | N12: =SUBSTITUTE(SUBSTITUTE(SUBSTITUTE(SUBSTITUTE(G12,"S:","")," H:",".")," D:",".")," C:",".") -> JT97.KQT6.J6.J54 | O12: =SUBSTITUTE(SUBSTITUTE(SUBSTITUTE(SUBSTITUTE(H12,"S:","")," H:",".")," D:",".")," C:",".") -> A63.A92.A87.A976 | P12: =SUBSTITUTE(SUBSTITUTE(SUBSTITUTE(SUBSTITUTE(I12,"S:","")," H:",".")," D:",".")," C:",".") -> Q54.J83.QT3.KT82 | R12: =IF('CSV Import'!I12="","",'CSV Import'!I12) -> East | S12: =IF('CSV Import'!J12="","",'CSV Import'!J12) -> pass 1NT | pass 2NT pass 3NT | pass pass pass | | T12: =IF('CSV Import'!K12="","",'CSV Import'!K12) -> 3NT | U12: =IF('CSV Import'!L12="","",'CSV Import'!L12) -> South | V12: =IF('CSV Import'!M12="","",'CSV Import'!M12) -> C2 | W12: =IF('CSV Import'!N12="","",'CSV Import'!N12) -> You are South and it is your bid. Decide what you would say, then click on BID. [BID 1NT]\nAces and Spaces is the description you often hear about this hand. But the REAL description is 16 points, balanced. So you open 1NT. Partner replies 2NT. What do you bid now? [BID 3NT]\nPartner is INVITING you to bid 3NT. If you have 17 points you should bid 3NT. If you have 15 points you should pass.\nWith 16 points you must make a judgement. This one is actually easy, despite the negative sound of "Aces and Spaces". In strength terms Aces are undervalued. Instead of being worth 4 points they are actually worth about 4.3 points. So you really do have a 17 point hand, and you bid 3NT.\nSouth plays 3NT. West leads the !C2.\nMake a Plan, then click NEXT. [NEXT]\nWinner count: !S 2 : !H 1 : !D 2 : !C 1 : Total = 6\nWow. Things do look a little Acey/Spacey. If the !Ds are 3-2, which is likely, you can establish 2 tricks there. You need one more and the best hope is the !CQ. There is a very good chance that West led from the !CK. So with a brief prayer to Brigidda (the Goddess of Bridge) you put up the !CQ. It wins the trick.\nNow you are on cruise-control. Play a !D to the !DA. Play another !D back to dummy's !DK (both defenders follow). Now a third !D sets up the rest of the suit.\nClick NEXT to see the full deal. [NEXT]\n
A13: ='CSV Import'!A13 -> 100Deals | B13: ='CSV Import'!B13 -> deal012.html | C13: ='CSV Import'!C13 -> 12 | E13: =IF('CSV Import'!D13="","",'CSV Import'!D13) -> BID+NEXT+ROTATE | F13: =IF('CSV Import'!E13="","",'CSV Import'!E13) -> S:85 H:J762 D:83 C:AKQ43 | G13: =IF('CSV Import'!F13="","",'CSV Import'!F13) -> S:QT43 H:54 D:JT964 C:95 | H13: =IF('CSV Import'!G13="","",'CSV Import'!G13) -> S:AK72 H:A83 D:AQ72 C:62 | I13: =IF('CSV Import'!H13="","",'CSV Import'!H13) -> S:J96 H:KQT9 D:K5 C:JT87 | K13: =4-COUNTIF(F13:I13,"") -> 4 | M13: =SUBSTITUTE(SUBSTITUTE(SUBSTITUTE(SUBSTITUTE(F13,"S:","")," H:",".")," D:",".")," C:",".") -> 85.J762.83.AKQ43 | N13: =SUBSTITUTE(SUBSTITUTE(SUBSTITUTE(SUBSTITUTE(G13,"S:","")," H:",".")," D:",".")," C:",".") -> QT43.54.JT964.95 | O13: =SUBSTITUTE(SUBSTITUTE(SUBSTITUTE(SUBSTITUTE(H13,"S:","")," H:",".")," D:",".")," C:",".") -> AK72.A83.AQ72.62 | P13: =SUBSTITUTE(SUBSTITUTE(SUBSTITUTE(SUBSTITUTE(I13,"S:","")," H:",".")," D:",".")," C:",".") -> J96.KQT9.K5.JT87 | R13: =IF('CSV Import'!I13="","",'CSV Import'!I13) -> North | S13: =IF('CSV Import'!J13="","",'CSV Import'!J13) -> 1NT | pass 2C pass 2S | pass 3NT pass pass | pass | T13: =IF('CSV Import'!K13="","",'CSV Import'!K13) -> 3NT | U13: =IF('CSV Import'!L13="","",'CSV Import'!L13) -> North | V13: =IF('CSV Import'!M13="","",'CSV Import'!M13) -> DJ | W13: =IF('CSV Import'!N13="","",'CSV Import'!N13) -> You are South and it is your bid. Decide what you would say, then click on BID. [BID 2!C]\nDespite the great !C suit, you have a 4-card Major. It is your duty to first seek an 8-card Major fit, so you bid 2!C (Stayman). Partner replies 2!S. What do you bid? [BID 3NT]\nWell, that wasn't the Major suit you were hoping for.\nBut with 11 points you have enough for game, so you bid 3NT.\nNorth would play 3NT.\nClick [ROTATE]\nSouth plays 3NT. West leads !DJ, East plays !DK.\nMake a Plan, then click NEXT. [NEXT]\nWinners: !S 2 : !H 1 : !D 2 : !C 3 : Total = 8\nThanks to the opening lead you get an extra !D winner. Well, since the finesse would have worked it really isn't extra, it's just nice to know about it early. You need to find one more winner and the !C suit beckons. A 3-3 split would be very nice, but a 4-2 is more likely. Even with a 4-2 split you can still make your fifth !C good - but you must be careful with entries.\nSince you have no immediate problem in any suit you can afford to give up the lead. So you play the !C2 from your hand and the !C3 from dummy. In other words, you duck a !C. Somebody will win this trick cheaply and no doubt play another !D. You don't mind at all - you win the !DQ, the !S A K, the !HA and dummy's !C A K Q 4, all of which are good.\nClick NEXT to see the full deal. [NEXT]\nIf you played a high !C first you would never have an entry back to dummy. You would have been forced to try to get there with the !HJ but as you can see, that wouldn't work.\nIf you had just played the !Cs from the top you would have made an overtrick when they split 3-3, but gone down when they split 4-2. Making an overtrick about 40% of the time is a high price to pay for going down the other 60%.
... A1174: ='CSV Import'!A1174 -> Weak2 | B1174: ='CSV Import'!B1174 -> deal20.html | C1174: ='CSV Import'!C1174 -> 20 | E1174: =IF('CSV Import'!D1174="","",'CSV Import'!D1174) -> BID | F1174: =IF('CSV Import'!E1174="","",'CSV Import'!E1174) -> S:A93 H:QJT754 D:74 C:J2 | G1174: =IF('CSV Import'!F1174="","",'CSV Import'!F1174) -> S:52 H:K962 D:KJ95 C:K64 | H1174: =IF('CSV Import'!G1174="","",'CSV Import'!G1174) -> S:KQJT84 H: D:Q86 C:AQ93 | I1174: =IF('CSV Import'!H1174="","",'CSV Import'!H1174) -> S:76 H:A83 D:AT32 C:T875 | K1174: =4-COUNTIF(F1174:I1174,"") -> 4 | M1174: =SUBSTITUTE(SUBSTITUTE(SUBSTITUTE(SUBSTITUTE(F1174,"S:","")," H:",".")," D:",".")," C:",".") -> A93.QJT754.74.J2 | N1174: =SUBSTITUTE(SUBSTITUTE(SUBSTITUTE(SUBSTITUTE(G1174,"S:","")," H:",".")," D:",".")," C:",".") -> 52.K962.KJ95.K64 | O1174: =SUBSTITUTE(SUBSTITUTE(SUBSTITUTE(SUBSTITUTE(H1174,"S:","")," H:",".")," D:",".")," C:",".") -> KQJT84..Q86.AQ93 | P1174: =SUBSTITUTE(SUBSTITUTE(SUBSTITUTE(SUBSTITUTE(I1174,"S:","")," H:",".")," D:",".")," C:",".") -> 76.A83.AT32.T875 | R1174: =IF('CSV Import'!I1174="","",'CSV Import'!I1174) -> North | S1174: =IF('CSV Import'!J1174="","",'CSV Import'!J1174) -> 2H pass 2S | pass 3S pass 4S | pass pass pass | T1174: =IF('CSV Import'!K1174="","",'CSV Import'!K1174) -> 4S | U1174: =IF('CSV Import'!L1174="","",'CSV Import'!L1174) -> South | V1174: =IF('CSV Import'!M1174="","",'CSV Import'!M1174) | W1174: =IF('CSV Import'!N1174="","",'CSV Import'!N1174) -> The bidding has gone as shown. Decide what you would bid, then click on BID above. [BID 2!S]\n\nYou know have just a 6-card !H fit so you can be no worse off in !Ss. You respond 2!S and partner raises to 3!S. What do you bid now? [BID 4!S]\n\nIt isn't a sure thing, but take a chance. Bid 4!S.

Sheet CSV Import
A1: Subfolder | B1: Filename | C1: DealNumber | D1: Kind | E1: NorthHand | F1: EastHand | G1: SouthHand | H1: WestHand | I1: Dealer | J1: Auction | K1: Contract | L1: Declarer | M1: Lead | N1: Analysis
A2: 100Deals | B2: deal001.html | C2: 1 | D2: BID+NEXT | E2: S:J86 H:A98 D:8653 C:AKQ | F2: S:A9 H:QT54 D:QJT2 C:JT3 | G2: S:Q53 H:762 D:AK4 C:8742 | H2: S:KT742 H:KJ3 D:97 C:965 | I2: North | J2: 1D pass 1NT | pass pass pass | K2: 1NT | L2: South | M2: S4 | N2: You are South and it is your bid. Decide what you would say, then click on BID. [BID 1NT]\nDo not be tempted to say 2!D, even with such good 3-card help. To support partner's minor suit opening you should have at least 4 cards in the suit. Remember he may have opened a 3-card suit.\nInstead you bid 1NT showing a balanced 6-10 point hand with no 4-card Major suit. Partner passes.\nSouth plays 1NT. West leads the !S4. East wins the !SA, then plays the !S9. West takes his !SK and leads another !S, East discarding a !H.\nMake a Plan, then click NEXT. [NEXT]\nTo make a PLAN for a Notrump contract you should count your winners.\nWinners: !S 1 : !H 1 : !D 2 : !C 3 : Total = 7\nFor this deal you see that you already have all the winners you need to make the contract. So you just want to be sure you don't do something stupid that would jeopardize those winners.\nYou win the !SQ, then lead to the !CA, !CK, !CQ. Everybody follows suit to these three tricks. Next you take the !HA. Then you play a small !D to your !DK, then play your !DA. You have now won your required 7 tricks, but you have a bonus. Since all the !Cs except the !C8 have been played your !C8 is now high and you make an overtrick.\nClick NEXT to see the complete deal. [NEXT]\nBut even with this type of hand you should make sure you take them in the right order. Here, if you had played the !DA and !DK BEFORE you played the !C A K Q you would have had no entry back to the fourth !C in your hand. In this case it was only an overtrick, in other deals it could make the difference between making and going down.
A3: 100Deals | B3: deal002.html | C3: 2 | D3: BID+NEXT | E3: S:74 H:KQJ3 D:AK75 C:863 | F3: S:J986 H:A5 D:Q32 C:QJT4 | G3: S:AKQ3 H:T982 D:J4 C:K72 | H3: S:T52 H:764 D:T986 C:A95 | I3: North | J3: 1D pass 1H | pass 2H pass 4H | pass pass pass | K3: 4H | L3: South | M3: DT | N3: You are South and it is your bid. Decide what you would say, then click on BID. [BID 1!H]\nA jump to 2NT would be descriptive, but your first goal is to seek a Major suit fit. When you have two 4-card Majors you should respond "up-the-line" so you bid 1!H. Partner says 2!H. What do you bid now? [BID 4!H]\nPartner would not support your !H suit without 4 cards so you have an 8-card Major fit. There is no point in bidding !Ss.\nPartner has at least 13 points and you have 13 so you bid the game.\nSouth plays 4!H. West leads the !DT.\nMake a Plan, then click NEXT. [NEXT]\nTo make a PLAN for a suit contract you should count your losers.\nLosers: !S 0 : !H 1 : !D 0 : !C 3 : Total = 4\nThere is nothing you can do about losing the Ace of trumps. The three !C losers would only happen if West has the !CA and East wins a trick early, (say with the !HA), and leads a !C through your !CK.\nYou can take care of this possibility by discarding a !C from dummy BEFORE you play trumps. So win the !DK, and play !SA, !SK, !SQ, discarding dummy's !C3 on the last one. Then pull trumps. You will end up losing two !Cs and the !HA.\nClick NEXT to see the Deal that could have set you. [NEXT]\nEast would win his !HA and would switch to a black suit to lead up to dummy's weakness. In this case he would surely lead the !CQ, and you would lose three !C tricks and be down before you started.\nMaking a PLAN is a necessary part of being a good Declarer and Visualizing what might happen is a necessary part of making a Plan.
A4: 100Deals | B4: deal003.html | C4: 3 | D4: BID+NEXT | E4: S:AQ5 H:74 D:Q962 C:AJT8 | F4: S:KT H:QJT982 D:83 C:652 | G4: S:872 H:K6 D:AKJ4 C:KQ74 | H4: S:J9643 H:A53 D:T75 C:93 | I4: East | J4: pass 1NT | pass 3NT pass pass | pass | K4: 3NT | L4: South | M4: S4 | N4: You are South and it is your bid. Decide what you would say, then click on BID. [BID 1NT]\nWith 16 points and a balanced hand you should open 1NT. Do not worry about the lack of a !S stopper, a 1NT opening does not guarantee stoppers in all four suits.\nPartner raises you to 3NT.\nSouth plays 3NT. West leads the !S4.\nMake a Plan, then click NEXT. [NEXT]\nWinners: !S 1 : !H 0 : !D 4 : !C 4 : Total = 9\nIt's nice to have a hand where the Winner count is 9. And guess what? West probably has the !SK, so you can finesse on the first trick for an overtrick.\nHOLD IT! JUST STEP AWAY FROM THE QUEEN OF SPADES AND NOBODY WILL GET HURT.\nWhat if you tried the finesse and East had the !SK? And what if he then switched to the !HQ? And what if your opponents then took the next 6 !H tricks? \nI think you get the idea. Win the !SA immediately and then take your other 8 tricks.\nClick NEXT to see the complete Deal. [NEXT]\nThis wasn't one of those times.
A5: 100Deals | B5: deal004.html | C5: 4 | D5: BID+NEXT | E5: S:KQJ H:A862 D:Q63 C:T94 | F5: S:72 H:QT43 D:AJ92 C:Q73 | G5: S:T98653 H:K7 D:84 C:AKJ | H5: S:A4 H:J95 D:KT75 C:8652 | I5: South | J5: 1S | pass 2H pass 2S | pass 4S pass pass | pass | K5: 4S | L5: South | M5: D5 | N5: You are South and it is your bid. Decide what you would say, then click on BID. [BID 1!S]\nDon't think of passing. With 11 HCP and 2 length points you open 1!S. Partner responds 2!H. What is your next bid? [BID 2!S]\nYou must bid and you want to show that you have a bare minimum. You don't want to say 2NT because of that doubleton nothing !D. So you rebid your 6-card !S suit. Partner bids 4!S and everybody passes.\nSouth plays 4!S. West leads the !D5 on which you play dummy's !D3. East wins !DJ, plays !DA, then !D2.\nMake a Plan, then click NEXT. [NEXT]\nLosers: !S 1 : !H 0 : !D 2 : !C 1 : Total = 4\nYou have already lost the 2 !Ds and you sure can't escape losing the Ace of trumps. So you mustnot lose a !C trick. So your Plan will be to pull trumps, then finesse East for the !CQ. \nYou ruff the third !D, play !Ss until the !SA appears. When you regain the lead you pull any outstanding trumps, play one high !C, (in case someone has a singleton !CQ), then enter dummy with the !HA and make the !C finesse. Half of the time you make the contract, the other half you don't.\nClick NEXT to see the full deal. [NEXT]\nIt's never great when the success of your contract depends on a finesse, but sometimes that's your only hope - a 50% chance.
A6: 100Deals | B6: deal005.html | C6: 5 | D6: BID+NEXT | E6: S:J64 H:Q7 D:A983 C:KQ76 | F6: S:A7 H:K653 D:762 C:T543 | G6: S:KQT3 H:A4 D:QJT5 C:AJ2 | H6: S:9852 H:JT982 D:K4 C:98 | I6: East | J6: pass 1NT | pass 3NT pass pass | pass | K6: 3NT | L6: South | M6: HJ | N6: You are South and it is your bid. Decide what you would say, then click on BID. [BID 1NT]\nYou have a very solid 17 points and a balanced hand. You open 1NT. Partner responds 3NT and you pass.\nSouth plays 3NT. West leads the !HJ. You hopefully put on the !HQ, but East plays the !HK.\nMake a Plan, then click NEXT. [NEXT]\nYou hopefully put on the !HQ, but East plays the !HK.\nWinners: !S 0 : !H 1 : !D 1 : !C 4 : Total = 6\nA hold-up won't help unless East had a doubleton !H, giving West a 7-card suit. So you win your !HA. The !S suit is solid after the !SA is played, but before you could enjoy those 3 tricks the defenders would have really enjoyed a bunch of !Hs.\nYour only hope is to win 8 more tricks before you lose the lead. That means the !D finesse had better work. At trick 2 you lead your !DQ, playing low from dummy if West doesn't cover. Repeat the finesse as necessary. When West has the !DK you will make your contract, and when East has the !DK you will go down. That's a 50% chance, just like most finesses. But remember, if you had tried to establish the !S suit instead of taking the finesse your chance of making 3NT would be 0%.\nClick for the full deal. [NEXT]\n
A7: 100Deals | B7: deal006.html | C7: 6 | D7: BID+NEXT+ROTATE | E7: S:QJT9 H:A5 D:7542 C:973 | F7: S:K63 H:QJT83 D:J C:KJ62 | G7: S:A2 H:K742 D:A863 C:AT5 | H7: S:8754 H:96 D:KQT9 C:Q84 | I7: North | J7: 1NT | pass pass pass | | K7: 1NT | L7: North | M7: HQ | N7: You are South and it is your bid. Decide what you would say, then click on BID. [BID pass]\nYou have 7 points so you know your side does not have a game. You also have no reason to think there is any better contract than 1NT. So you pass.\nNorth would play 1NT. To make life more convenient the hands will be rotated so that South becomes declarer. \nClick ROTATE. [ROTATE]\nSouth plays 1NT. West leads the !HQ.\nMake a Plan, then click NEXT. [NEXT]\nWinners: !S 1 : !H 2 : !D 1 : !C 1 : Total = 5\nYou need two more winners. Even if the !Ds split 3-2 you can get only one more from that suit. So clearly you must use the !S suit. Since you have only one entry to dummy you must save it until the right time.\nWin the first trick with the !HK. Then play !SA followed by !S2. Continue playing !Ss until the !SK is forced out. Win whatever they play next and play your other winners. You cannot be stopped from taking 7 tricks.\nClick NEXT to see the full deal. [NEXT]\nWhat would you try next? A !S finesse? Whether West took his !SK right then or later you would go down. You could never reach dummy again.
A8: 100Deals | B8: deal007.html | C8: 7 | D8: BID+NEXT | E8: S:T64 H:KJ7 D:86 C:J7532 | F8: S:982 H:5 D:QT742 C:AK96 | G8: S:QJ5 H:AQT963 D:AK5 C:Q | H8: S:AK73 H:842 D:J93 C:T84 | I8: South | J8: 1H | pass 2H pass 4H | pass pass pass | | K8: 4H | L8: South | M8: SA | N8: You are South and it is your bid. Decide what you would say, then click on BID. [BID 4!H]\nYou have a nice hand, but 20 points is not strong enough to open 2!C. \nSo you open 1!H. Partner raises to 2!H. What do you bid now? [BID pass]\nPartner's raise to 2!H shows 6-10 points. You figure that should be enough for game but even if he has the full T you are not in slam range. So you bid the game. \nSouth plays 4!H. West leads !SA, then switches to !H2.\nMake a Plan, then click NEXT. [NEXT]\nLosers: !S 2 : !H 0 : !D 1 : !C 1 : Total = 4\nIt's a good thing you stopped at game - partner's hand is about as bad as it could be.\nThe PLAN turns out simple. You can't avoid either of the three black losers so you must eliminate the !D loser. You can ruff it in dummy. Just to be safe you pull one more round of trumps, then play !DA, !DK and !D5, ruffing in dummy. You will eventually get to your hand (with a !S or a !C ruff) and pull the last trump.\nClick NEXT to see the full deal. [NEXT]\nOnly a real beginner would have pulled all the trumps and not been able to ruff that !D.
A9: 100Deals | B9: deal008.html | C9: 8 | D9: BID+NEXT+ROTATE | E9: S:74 H:K53 D:AK962 C:KQ3 | F9: S:QJT82 H:T86 D:754 C:A5 | G9: S:A9 H:AJ2 D:QJ3 C:JT862 | H9: S:K653 H:Q974 D:T8 C:974 | I9: West | J9: pass 1C | pass 1D pass 1NT | pass 3NT pass pass | pass | K9: 3NT | L9: North | M9: SQ | N9: You are South and it is your bid. Decide what you would say, then click on BID. [BID pass]\nWith 16 points as Responder you are not quite strong enough for a jump-shift to 2 !D. That requires at least 17 points. A jump to 3NT fits the point range (16-18) but promises a stopper in all unbid suits. So instead you bid 1!D, knowing partner is forced to keep the bidding alive. He now replies 1NT. What is your next bid? [BID pass]\nUntil now you were thinking the hand might end up in a slam. Now, with partner's minimum rebid, you happily say 3NT which partner passes.\nNorth would play 3NT. \nClick [ROTATE]\nSouth plays 3NT. West leads the !SQ. East puts on the !SK.\nMake a Plan, then click NEXT. [NEXT]\nWinners: !S 1 : !H 2 : !D 5 : !C 0 : Total = 8\nLet's say you hold up on the first !S, hoping they switch suits. HA! They aren't about to switch suits and they drive out your !SA at trick 2. That actually clears the situation up and makes this plan pretty simple to make.\nYou have taken 1 !S, and you will surely make 5 !Ds. Despite the solidity of those !Cs you dare not try to win a !C trick, because the defenders will pounce on that first !C and then win a bunch of !S tricks. \nSo that makes it clear that you need 3 !H tricks, and there's only one way to get them. After taking your five !D tricks, play a !H to the !HK, then a !H back, finessing the !HJ. Half of the time you will make this contract, the other half of the time they will bury you with !Ss.\nClick NEXT to see the full deal. [NEXT]\n
A10: 100Deals | B10: deal009.html | C10: 9 | D10: BID+NEXT+ROTATE | E10: S:952 H:KQ92 D:KQ83 C:J7 | F10: S:KQJ8 H: D:9764 C:QT652 | G10: S:T63 H:AT754 D:AJ2 C:AK | H10: S:A74 H:J863 D:T5 C:9843 | I10: North | J10: 1H | pass 3H pass 4H | pass pass pass | K10: 4H | L10: North | N10: You are South and it is your bid. Decide what you would say, then click on BID. [BID 3!H]\nYou have 12 points which isn't quite enough to force to game.\nIt is just right for a limit raise though, so you bid 3!H.\nPartner does bid the game.\nNorth would play 4!H.\nClick [ROTATE]\nSouth plays 4!H. The defense takes the first three !S tricks, then switches to a !C.\nMake a Plan, then click NEXT. [NEXT]\nLosers: !S 3 : !H ?? : !D 0 : !C 0 : Total = 3+??\nWith no more outside losers your task is very very simple:DO NOT LOSE A TRUMP TRICK.\nThere is no problem if trumps split 2-2 or 3-1, so you can put your mind to 4-0 splits only. If West holds !H J 8 6 3 then it won't matter whether your first trump play is !HA or !HK, you will still be able to finesse the !HJ. But if East holds !H J 8 6 3 it is vital that you first play either the !HK or !HQ. If you start with the !HA you will have lost your finesse position. The general rule is to first play a high trump from the hand that has two. That preserves a finesse through either defender's !H J x x x.\nClick NEXT to see the full deal. [NEXT]\nNext visualize the situation if your first play was the !HK. West would show out and you would play the !HQ, then a small !H finessing your !HT. \nFinally visualize the situation if your first play was the !HK and it was East who showed out. You would play a small !H to your !HA, then lead a !H toward dummy finessing with the !H9.\nUsing the correct Plan guarantees the contract however !Hs split.
A11: 100Deals | B11: deal010.html | C11: 10 | D11: BID+NEXT | E11: S:KQ92 H:952 D:K7 C:KQ83 | F11: S: H:A874 D:QJ632 C:T764 | G11: S:A8754 H:T63 D:A8 C:AJ2 | H11: S:JT63 H:KQJ D:T954 C:95 | I11: North | J11: 1C pass 1S | pass 2S pass 4S | pass pass pass | K11: 4S | L11: South | N11: You are South and it is your bid. Decide what you would say, then click on BID. [BID 1!S]\nPartner has opened and you have 14 points. You know you belong in game but there is no need to jump and use up bidding space. You respond 1!S.\nPartner now bids 2!S. What do you bid next? [BID 4!S]\nYou know you should be in game and now you know the suit. You bid 4!S.\nSouth plays 4!S. The defense quickly takes three !H tricks, then switches to a !D.\nMake a Plan, then click NEXT. [NEXT]\nLosers: !S 0? : !H 3 : !D 0 : !C 0 : Total = 3?\nThis Deal is VERY similar to Deal 9 in that you are only worried about a 4-0 trump split. The reason that it shows up right here is to point out the difference between J 8 6 3 and J T 6 3.\nIf East holds !S J T 6 3 then there is nothing you can do about it - you will go down. If you lead a !S from dummy he will "split his honors" by playing the !ST. This will force your !SA and he can just sit back and wait for his !SJ to make a trick.\nBut if it is West with !S J T 6 3 you can keep him from winning a !S trick, IF YOUR FIRST !S PLAY IS THE !SA. East shows out and you play a small !S toward dummy's !S K Q 9. If West plays low you insert the !S9, if he plays one of his honors you win it, then return to your hand and finesse him out of the other honor.\nClick NEXT to see the full deal. [NEXT]\nIf your first !S was !SK or !SQ then it would be too late.\nClick NEXT to see an alternate deal. [NEXT]\nTo summarize: If you are missing J x x x your first play should be from the hand with two honors. Then you will be able to finesse in either direction. If you are missing J T x x your first play should be honor from the hand with only one. This will leave you with a double-finesse position in one direction. If the other defender has the trumps there is nothing you can do.
A12: 100Deals | B12: deal011.html | C12: 11 | D12: BID+NEXT | E12: S:K82 H:754 D:K9542 C:Q3 | F12: S:JT97 H:KQT6 D:J6 C:J54 | G12: S:A63 H:A92 D:A87 C:A976 | H12: S:Q54 H:J83 D:QT3 C:KT82 | I12: East | J12: pass 1NT | pass 2NT pass 3NT | pass pass pass | | K12: 3NT | L12: South | M12: C2 | N12: You are South and it is your bid. Decide what you would say, then click on BID. [BID 1NT]\nAces and Spaces is the description you often hear about this hand. But the REAL description is 16 points, balanced. So you open 1NT. Partner replies 2NT. What do you bid now? [BID 3NT]\nPartner is INVITING you to bid 3NT. If you have 17 points you should bid 3NT. If you have 15 points you should pass.\nWith 16 points you must make a judgement. This one is actually easy, despite the negative sound of "Aces and Spaces". In strength terms Aces are undervalued. Instead of being worth 4 points they are actually worth about 4.3 points. So you really do have a 17 point hand, and you bid 3NT.\nSouth plays 3NT. West leads the !C2.\nMake a Plan, then click NEXT. [NEXT]\nWinner count: !S 2 : !H 1 : !D 2 : !C 1 : Total = 6\nWow. Things do look a little Acey/Spacey. If the !Ds are 3-2, which is likely, you can establish 2 tricks there. You need one more and the best hope is the !CQ. There is a very good chance that West led from the !CK. So with a brief prayer to Brigidda (the Goddess of Bridge) you put up the !CQ. It wins the trick.\nNow you are on cruise-control. Play a !D to the !DA. Play another !D back to dummy's !DK (both defenders follow). Now a third !D sets up the rest of the suit.\nClick NEXT to see the full deal. [NEXT]\n
A13: 100Deals | B13: deal012.html | C13: 12 | D13: BID+NEXT+ROTATE | E13: S:85 H:J762 D:83 C:AKQ43 | F13: S:QT43 H:54 D:JT964 C:95 | G13: S:AK72 H:A83 D:AQ72 C:62 | H13: S:J96 H:KQT9 D:K5 C:JT87 | I13: North | J13: 1NT | pass 2C pass 2S | pass 3NT pass pass | pass | K13: 3NT | L13: North | M13: DJ | N13: You are South and it is your bid. Decide what you would say, then click on BID. [BID 2!C]\nDespite the great !C suit, you have a 4-card Major. It is your duty to first seek an 8-card Major fit, so you bid 2!C (Stayman). Partner replies 2!S. What do you bid? [BID 3NT]\nWell, that wasn't the Major suit you were hoping for.\nBut with 11 points you have enough for game, so you bid 3NT.\nNorth would play 3NT.\nClick [ROTATE]\nSouth plays 3NT. West leads !DJ, East plays !DK.\nMake a Plan, then click NEXT. [NEXT]\nWinners: !S 2 : !H 1 : !D 2 : !C 3 : Total = 8\nThanks to the opening lead you get an extra !D winner. Well, since the finesse would have worked it really isn't extra, it's just nice to know about it early. You need to find one more winner and the !C suit beckons. A 3-3 split would be very nice, but a 4-2 is more likely. Even with a 4-2 split you can still make your fifth !C good - but you must be careful with entries.\nSince you have no immediate problem in any suit you can afford to give up the lead. So you play the !C2 from your hand and the !C3 from dummy. In other words, you duck a !C. Somebody will win this trick cheaply and no doubt play another !D. You don't mind at all - you win the !DQ, the !S A K, the !HA and dummy's !C A K Q 4, all of which are good.\nClick NEXT to see the full deal. [NEXT]\nIf you played a high !C first you would never have an entry back to dummy. You would have been forced to try to get there with the !HJ but as you can see, that wouldn't work.\nIf you had just played the !Cs from the top you would have made an overtrick when they split 3-3, but gone down when they split 4-2. Making an overtrick about 40% of the time is a high price to pay for going down the other 60%.
A14: 100Deals | B14: deal013.html | C14: 13 | D14: BID+NEXT+ROTATE | E14: S: H:T965 D:AT9643 C:Q72 | F14: S:Q986 H:KQJ3 D:KQ C:853 | G14: S:AJT7542 H: D:75 C:AKJT | H14: S:K3 H:A8742 D:J82 C:964 | I14: North | J14: 1S | pass 1NT pass 4S | pass pass pass | K14: 4S | L14: North | M14: HK | N14: You are South and it is your bid. Decide what you would say, then click on BID. [BID 1NT]\nThis is awkward. With 8 points you must respond, but you cannot bid a new suit at the 2-level without 11 or more. Although you are far from balanced you must say 1NT.\nYou might as well not have worried. Partner jumps to 4!S and you pass.\nNorth would play 4!S.\nClick [ROTATE]\nSouth plays 4!S. West leads the !HK.\nMake a Plan, then click NEXT. [NEXT]\nLosers: !S ? : !H 0 : !D 1 : !C 0 : Total = ?\nThat 1 !D loser is definite. So instead of guessing how many !S losers you have, just approach it from the viewpoint that you can afford 2 but not 3.\nIf the missing !Ss split 3-3 then your life is easy. You play !SA, then any !S. Win their return and play any !S. The defense can win two !Ss but no more.\nIt's when the !Ss are splitting 4-2 that you must be careful. If somebody has !S K Q 9 3 for example you will go down. The one important distribution to guard against is a doubleton honor in one hand. In this case your second !S play must be a LOW !S. When this drives out one honor your !S J T can insure that only one more trick is lost.\nClick NEXT to see the full deal. [NEXT]\nBut if your second !S play is a small !S East will win the !SK and you will be left with the !S J T to deal with West's !S Q 9, holding him to just one more trick.
A15: 100Deals | B15: deal014.html | C15: 14 | D15: BID+NEXT+ROTATE | E15: S:A74 H:KT953 D:J53 C:Q3 | F15: S:JT92 H:862 D:87 C:J975 | G15: S:K63 H:QJ D:AK42 C:AT64 | H15: S:Q85 H:A74 D:QT96 C:K82 | I15: North | J15: 1NT | pass 3H pass 3NT | pass pass pass | K15: 3NT | L15: North | M15: SJ | N15: You are South and it is your bid. Decide what you would say, then click on BID.\n<i>You and partner do NOT play Jacoby Transfer Bids</i>. [BID 3!H]\nWith 11 points you know you want to reach game since partner has at least 15. However, you aren't sure at this point just which game to reach. If you knew partner held 3!Hs you'd choose 4!H since you would have an 8-card Major fit. On the other hand, if you knew partner had only a doubleton !H you would choose 3NT, which would probably be better. So you jump to 3!H. This bid tells partner to "Pick a Game". \nHe picks 3NT.\nNorth would play 3NT.\nClick [ROTATE]\nSouth plays 3NT. West leads the !SJ.\nMake a Plan, then click NEXT. [NEXT]\nWinner count: !S 2 : !H 0 : !D 2 : !C 1 : Total = 5\nAlthough the !D and !C suits offer the possibility for creating a winner it is evident that you really need to bring in the !Hs. By driving out the !HA you will establish the 4 winners that you need. The problem is that when you play !HQ then !HJ a good defender will hold up his !HA. You could get to dummy with the !SA and continue !Hs, but you would no longer have a sure entry to get back to those winners.\nThere is an almost foolproof plan. Win the first trick with your !SK (saving dummy's !SA). Lead !HQ, then !HJ, OVERTAKING WITH DUMMY'S !HK. Now continue the !HT driving out the !HA. You will be able to reach the !H tricks with the !SA.\nClick NEXT to see the full deal. [NEXT]\n
A16: 100Deals | B16: deal015.html | C16: 15 | D16: BID+NEXT | E16: S:954 H:T873 D:AQ62 C:75 | F16: S:62 H:52 D:T753 C:A8432 | G16: S:A73 H:KJ964 D:KJ C:QJT | H16: S:KQJT8 H:AQ D:984 C:K96 | I16: South | J16: 1H | 1S 2H pass pass | pass | K16: 2H | L16: South | M16: SK | N16: You are South and it is your bid. Decide what you would say, then click on BID. [BID 1!H]\nYou may not have had a problem with this opening bid, but be assured that many would. The hand meets all the requirements for an opening 1NT bid, balanced distribution and 16 points. So lots of good players would open 1NT. However, there is the question of the 5-card Major. Another group of good players don't open 1NT when their hand contains a 5-card Major.\nSo let us agree that either could be right and say that you chose 1!H. West overcalls 1!S, partner says 2!H and you pass.\nSouth plays 2!H. West leads the !SK.\nMake a Plan, then click NEXT. [NEXT]\nLosers: !S 2 : !H 2 : !D 0 : !C 2 : Total = 6\nYou might get lucky in the trump suit and only lose one trick, but you can't count on it. Dummy's !D suit has two extra winners, but there is the problem of transportation. By the time you get to enjoy those two winners you might have already lost six tricks.\nOne thing should be crystal clear. If you now lead a trump the defenders will win and cash 2 !Ss. You can avoid this by waiting on the trumps and playing !DK, then overtake the !DJ with dummy's !DQ. Then play !DA and discard a !S. Now from dummy you can lead a !H and perhaps play your !HK but even if it loses you will still make the contract.\nClickfor the full deal. [NEXT]\nMake sure you visualize how the play would have gone if you had played a trump to the second trick. When you see clearly the bad things that are likely to happen you will look harder for a remedy. When confronted with a hand such as this many beginning (or careless) players just automatically start trying to pull trumps. And many times they go down on hands that could have been made.
A17: 100Deals | B17: deal016.html | C17: 16 | D17: BID+NEXT+ROTATE | E17: S:95 H:A742 D:5 C:KQT983 | F17: S:QJT4 H:QT93 D:QT43 C:5 | G17: S:AK3 H:K865 D:9762 C:AJ | H17: S:8762 H:J D:AKJ8 C:7642 | I17: North | J17: 1NT | pass 2C pass 2H | pass 4H pass pass | pass | K17: 4H | L17: North | M17: SQ | N17: You are South and it is your bid. Decide what you would say, then click on BID. [BID 2!C]\nIt is tempting to bid 3NT and hope partner can use your !C suit. But you have something very important in your hand - a 4-card !H suit.\nSo you bid 2!C. (Stayman, not your !C suit!) Partner replies 2!H. What do you say next? [BID 4!H]\nHe who knows, goes. You have 11 points and 4 !Hs. Partner has at least 15 points and 4 !Hs. So you bid the game. \nNorth would play 4!H.\nClick [ROTATE]\nSouth plays 4!H. West leads the !SQ.\nMake a Plan, then click NEXT. [NEXT]\nSouth plays 4!H. West leads the !SQ.\nLosers: !S 0 : !H 1 or 2 : !D 1 : !C 0 : Total = 2 or 3\nThis PLAN looks awfully simple. Win the !S, play !HA, !HK, then give up a !H. When you get back in run the !Cs.\nBut when you play the second high !H East shows out.\nMake another Plan, then click NEXT. [NEXT]\nLet's start over. Play !HK, then !HA. East shows out. If you play another !H West will pull all the trumps and they will start winning !D tricks. Lots of !D tricks.\nSo don't lead the third !H. Leave West with his two master trumps and start playing !C winners. West will eventually ruff in with one of his high trumps and perhaps take a !D trick. But you have trump control and can get in again and reach dummy with a ruff to continue !Cs. All West can do is get his one more trump.\nClick NEXT to see the full deal. [NEXT]\nThis hand is much rarer - leaving TWO master trumps out. But you can see that it is the correct technique.
A18: 100Deals | B18: deal017.html | C18: 17 | D18: BID+NEXT | E18: S:A763 H:84 D:J76 C:A964 | F18: S:QJ98 H:QT3 D:A942 C:T7 | G18: S:K52 H:A96 D:KQ5 C:KQJ2 | H18: S:T4 H:KJ752 D:T83 C:853 | I18: East | J18: pass 1C | pass 1S pass 2NT | pass 3NT pass pass | pass | K18: 3NT | L18: South | M18: H5 | N18: You are South and it is your bid. Decide what you would say, then click on BID. [BID 1!C]\nThis sure looks like an opening 1NT hand, except for one little thing - it is too strong. Make sure you open 1NT ONLY with hands containing 15-17 points. For this one you open 1!C. Partner responds 1!S. What do you bid next? [BID 2NT]\nDo not support partner's Major suit response with only 3 cards. It is good to raise partner's Major suit OPENING with 3 trumps because he guarantees a 5-card suit. As a RESPONSE he only promises a 4-card suit, so you should have 4 in the suit to give immediate support.\nIn fact you have a perfect bid. With a balanced hand and 18-19 points you open 1 of a suit, then jump in Notrump. Holding 18 points you bid 2NT and partner raises to 3NT.\nSouth plays 3NT. West leads the !H5. East plays the !HQ.\nMake a Plan, then click NEXT. [NEXT]\nWinner count: !S 2 : !H 1 : !D 0 : !C 4 : Total = 7\nYou need 2 more winners and they will come from the !D suit once you have forced out the !DA. There is a problem though. When the opponents get the lead with the !DA they might cash 4 !H tricks. Of course if it is East who wins the !DA and if he doesn't have a !H to play then all will be well. So you don't take your !HA on the first trick, nor do you take it on the second trick. At trick 3 you have no choice so you win your !HA. \nNow you can take your 4 !C tricks if you like. Then lead a !D honor. If they don't take their !DA on this trick you play another !D honor. One of the defenders will win this trick. If it is East you will make your contract, if it is West you will go down.\nClick NEXT to see the full deal. [NEXT]\nNotice that if West was the one who had the !DA then you would go down despite your hold-up play. This PLAN is not a guarantee - but if you follow it you will make the contract 50% of the time. If you don't follow it you will make the contract 0% of the time.
A19: 100Deals | B19: deal018.html | C19: 18 | D19: BID+NEXT | E19: S:AQJ2 H:T742 D:T9 C:AQ4 | F19: S:K865 H:9 D:KQJ4 C:KJT7 | G19: S:3 H:AKQJ83 D:863 C:963 | H19: S:T974 H:65 D:A752 C:852 | I19: East | J19: 1D 1H | pass 4H pass pass | pass | K19: 4H | L19: South | M19: DA | N19: You are South and it is your bid. Decide what you would say, then click on BID. [BID 1!H]\nWith 12 points and an excellent suit you overcall 1!H.\nPartner raises to 4!H and everyone passes.\nSouth plays 4!H. West leads the !DA and the defense wins two high !Ds then switches to a trump.\nMake a Plan, then click NEXT. [NEXT]\nLosers: !S 0 : !H 0 : !D 2 : !C 2 : Total = 4\nThe two !D losers are already lost, so you must eliminate a !C loser. If West has the !CK then a simple finesse will win the day. That would be a 50% chance, right? WRONG! That would be a 0% chance. You and partner hold 23 HCP. West has already produced 4 HCP with the !DA, and if he had 3 more that would mean East opened with only 10 points. Very doubtful.\nSo face it, East has the !CK.\nHowever, dummy has some nice !S cards. So you pull the last trump, play your !S3 to dummy's !SA, then lead the !SQ. If East puts on his !SK (which you know he must have) you ruff it. Then enter dummy with a !D ruff and discard the small !C on the good !SJ. If East doesn't play his !SK you discard your !C loser immediately.\nClickfor the full deal. [NEXT]\nThis was a perfect example. After the opening lead it was easy to deduce that all the rest of the high cards had to be in the East hand.
A20: 100Deals | B20: deal019.html | C20: 19 | D20: BID+NEXT | E20: S:985 H:Q D:A7643 C:AT92 | F20: S:QT2 H:98743 D:T9 C:854 | G20: S:AK764 H:AJT D:8 C:KQJ7 | H20: S:J3 H:K652 D:KQJ52 C:63 | I20: South | J20: 1S | pass 3S pass 4NT | pass 5H pass 6S | pass pass pass | K20: 6S | L20: South | M20: DK | N20: You are South and it is your bid. Decide what you would say, then click on BID. [BID 1!S]\nYou open 1!S and partner jumps to 3!S.\nWhat do you bid next? [BID 4NT]\nWow. It looks like you might have a great fit. You bid 4NT and partner responds 5!H.\nWhat do you bid next?\nMake a Plan, then click NEXT. [NEXT]\nPartner shows 2 Aces so you bid 6!S.\nSouth plays 6!S. West leads the !DK.\nMake a Plan, then click NEXT. [NEXT]\nLosers: !S 1? : !H 1 : !D 0 : !C 0 : Total = 2?\nIf trumps don't split 3-2 you will definitely go down 1, so assume they do split. You could finesse East once in !Hs, or use a ruffing finesse on West, but the cleanest approach is just to ruff two !Hs in dummy. Of course you must do this before you pull trumps.\nWin the !DA in dummy. Play the !HQ to the !HA and ruff the !HT with dummy's !S8. Play the !S5 to your !SA and ruff the !HJ with dummy's !S9.\nReturn to your hand with a !C and pull another round of trumps with your !SK. Leaving the master trump out start playing !C winners. Someone may ruff with their master trump but that's the only trick they will get.\nClick NEXT to see the full deal. [NEXT]\nBut that would have been all for nothing if South had not found the PLAN to make it.
A21: 100Deals | B21: deal020.html | C21: 20 | D21: BID+NEXT+ROTATE | E21: S:9764 H:K8 D:AT62 C:AQ3 | F21: S:A32 H:QJT72 D:J C:9862 | G21: S:K5 H:A94 D:K9873 C:KT5 | H21: S:QJT8 H:653 D:Q54 C:J74 | I21: North | J21: 1D | 1S pass 1NT | pass 3NT pass pass | pass | K21: 3NT | L21: North | M21: HQ | N21: You are South and it is your bid. Decide what you would say, then click on BID. [BID pass]\nWith 13 points and 4 of partner's minor suit you may be tempted to say 2NT or 3!D. Both these temptations should be resisted - your first obligation is to show a 4-card Major if you have one. As poor as the suit is, you still respond 1!S. \nPartner comes back with 1NT. What do you bid now? (Hint: don't rebid the !Ss.) [BID pass]\nPartner has 13/14 points and a balanced hand. You have 13 points and a balanced hand. How about 3NT?\nNorth would play 3NT.\nClick [ROTATE]\nSouth plays 3NT. West leads the !HQ. \nMake a Plan, then click NEXT. [NEXT]\nWinner count: !S 0 : !H 2 : !D 2 : !C 3 : Total = 7\nYou need two more winners and you can almost surely get them in !Ds. In fact, if the suit splits 2-2 you could actually get three more winners. But the danger here is that if they DON'T split 2-2 and if East happens to win the third !D he might lead a !S. And that might lead to disaster!\nInstead, you allow for the possibility that !Ds may not split evenly and you make sure East (the Danger hand) doesn't get the lead. Win the !HK in dummy. Play the !DA, (which happens to draw the !DJ from West), then play a small !D and finesse with the !D9. If West can win the trick then the !Ds have split 2-2 and your other 3 !Ds are good. Most importantly though, West cannot lead a !S without giving you a trick with your !SK. If the finesse works, you make 5 !D tricks.\nClick NEXT to see the full deal. [NEXT]\nHere the bad thing would be for East to get the lead and play a !S. In this case you were able to avoid the bad situation by playing a suit differently than you might have done if there were no danger.
A22: 100Deals | B22: deal021.html | C22: 21 | D22: BID+NEXT | E22: S:74 H:K532 D:954 C:QJ83 | F22: S:QJ2 H:A764 D:JT73 C:T5 | G22: S:AK9865 H:9 D:AQ6 C:AK2 | H22: S:T3 H:QJT8 D:K82 C:9764 | I22: East | J22: pass 2C | pass 2D pass 2S | pass 2NT pass 3S | pass 4S pass pass | pass | K22: 4S | L22: South | M22: HQ | N22: You are South and it is your bid. Decide what you would say, then click on BID. [BID 2!C]\nWith 22 points you are too strong to open with a 1-bid.\nYou start with a forcing 2!C, partner responds 2!D. This is a "waiting" bid, showing 0-7 points. What do you bid now? [BID 2!S]\nNo need to jump. If you say anything other than 2NT partner is forced to bid again.\nYou bid 2!S and it is partner who says 2NT. What do you bid now?\nMake a Plan, then click NEXT. [NEXT]\nAlways keep in mind that you don't need to bid the same values twice. Partner knows that you have 22 or more points and knows that you have a good !S suit. So all you do at this point is rebid your !Ss to show that it is a 6-card suit.\nYou bid 3!S and partner raises you to game.\nSouth plays 4!S. West leads the !HQ.\nMake a Plan, then click NEXT. [NEXT]\nLosers: !S 1? : !H 1 : !D 2 : !C 0 : Total = 4?\nThat question mark means that if !Ss don't split 3-2 you will have 2 losers in which case the !D finesse will just have to work. However, the 3-2 split will probably occur, so you make your PLAN based on that.\nUnless West is a complete moron dummy's !HK is a goner no matter what you do. So you duck, then ruff the !HJ continuation. Next you play !SA, !SK, both defenders following. At this point one defender still holds the master !SQ and you must decide whether to leave it outstanding or force them to play it. \nWhen dummy has a side suit you want to run but no outside entries it usually pays to drive out the master trump. So you play another !S and East wins the !SQ. He now plays a !D and you hopefully play the !DQ, but West takes the !DK and plays another !D. You are now in control. Win the !DA and play 4 rounds of !Cs, discarding your !D loser. \nClick NEXT to see the full deal. [NEXT]\nYou would have played !CA, !C K, then a small !C to dummy's !CJ. East would ruff this with his !SQ and you would never be able to reach dummy's !CJ. You would be down 1, losing 1 !S, 1 !H and 2 !Ds.
A23: 100Deals | B23: deal022.html | C23: 22 | D23: BID+NEXT | E23: S:9873 H:964 D:A85 C:AKQ | F23: S:KJ2 H:QJ72 D:73 C:T954 | G23: S:T654 H:AK3 D:9642 C:J8 | H23: S:AQ H:T85 D:KQJT C:7632 | I23: North | J23: 1C pass 1S | pass 2S pass pass | pass | K23: 2S | L23: South | M23: DK | N23: You are South and it is your bid. Decide what you would say, then click on BID. [BID 1!S]\nThere are three legitimate choices, 1!D, 1!S or 1NT.\nYou should always show a Major suit if you can, even a poor one like this.\nYou bid 1!S. Partner says 2!S and it is your bid. [BID pass]\nPartner has a minimum opener. You pass in a flash.\nSouth plays 2!S. West leads the !DK.\nMake a Plan, then click NEXT. [NEXT]\nLosers: !S 3? : !H 1 : !D 2 : !C 0 : Total = 6?\nYour !H loser can disappear on dummy's third !C.\nIf !Ss split 3-2 you can hold your losers in the suit to 3 as long as the defenders don't get a ruff. But if the defender with a doubleton trump happened to get a ruff then your trump losers would go to 4. You should lead trumps to try to prevent this.\nSo win the !DA and lead a !S. West will win and play 3 high !Ds. You ruff the third one in dummy. East may over-ruff, and if he does you can hope that he was the defender who started with 3 trumps. Suppose East now leads a !H. You win in your hand and play another trump, happily observing the !SK and !SA both fall. You win the rest of the tricks, discarding your !H loser on dummy's third !C.\nClick NEXT to see the full deal. [NEXT]\nYou were a little lucky that the defender who got the ruff, East, was the one who started with 3 trumps.
... A95: 100Deals | B95: deal094.html | C95: 94 | D95: BID+NEXT | E95: S:62 H:QT4 D:T9653 C:AQ7 | F95: S:JT74 H:73 D:KQ82 C:543 | G95: S:KQ5 H:KJ985 D:A7 C:K86 | H95: S:A983 H:A62 D:J4 C:JT92 | I95: South | J95: 1H | pass 2H pass 3C | pass 4H pass pass | pass | K95: 4H | L95: South | M95: CJ | N95: You are South and it is your bid. Decide what you would say, then click on BID. [BID 1!H]\nYou have a valid opening 1NT bid. You also have a valid opening 1!H bid. It is up to you and your partner to agree on whether you will open 1NT when you hold a 5-card Major.\nFor the purpose of this Deal, and not choosing sides, you open 1!H. Partner responds 2!H. [BID 3!C]\nYou agree on Where, now you must figure out How High. Add partner's 6-T to your 17 and you get 23-27. In other words you might have enough for game if partner has a maximum. \nYou want to make an invitational bid and it is ok to now bid 3!H. Partner will understand what you mean and will either pass or bid 4!H, depending on his hand.\nBut you can also bid any other suit and it will have the same invitational quality to it, but it will give partner the information about where you could use some help. This is called a Help Suit Game Try. In this case you bid 3!C.\nPartner, with 9 points and help for !Cs, bids 4!H.\nSouth plays 4!H. West leads the !CJ.\nMake a Plan, then click NEXT. [NEXT]\nLosers: !S 2 : !H 1 : !D 1 : !C 0 : Total = 4\nThe !SA and the !HA definitely won't go away. And the !D loser is pretty sure also. However, the second !S loser can be eliminated either by leading up to the !S K Q 5 or by ruffing it in dummy.\nSuppose you win the !C and play one round of trumps. Oops, it is now too late to make the contract. Someone can win the !HA and play another !H. Then, whoever takes the !SA can lead a third !H and you can no longer ruff your !S.\nTry this instead. Win the !C in dummy and play a small !S to your !SQ. Assume West wins the !SA and leads !HA and another !H. You win this in your hand, play !SK and ruff your last !S with dummy's last trump. Now get to your hand, pull trumps and give up a !D at the end.\nClick NEXT to see the full deal. [NEXT]\nSuppose when you led toward your !SQ it held the trick. Would you be convinced that East musthold the !SA and change your plan? Would you then pull trumps and let your contract depend on that assumption? I hope not.
A96: 100Deals | B96: deal095.html | C96: 95 | D96: BID+NEXT | E96: S:J642 H:Q6 D:AK42 C:K73 | F96: S:985 H:A532 D:J7 C:J965 | G96: S:AK H:T98 D:865 C:AQT82 | H96: S:QT73 H:KJ74 D:QT93 C:4 | I96: East | J96: pass 1C | pass 1S pass 1NT | pass 3NT pass pass | pass | K96: 3NT | L96: South | N96: You are South and it is your bid. Decide what you would say, then click on BID. [BID 1!C]\nWith 14 points and only one biddable suit this was a snap. You open 1!C. Partner responds with 1!S. What do you bid? [BID 1NT]\nThis one isn't such a snap. You sure cannot support !Ss with only 2 of them, even good ones. You aren't supposed to rebid your !Cs without a 6-card suit. You hate to bid Notrump with neither of the two red suits stopped, and you cannot pass. So you bite the bullet and say 1NT. Partner jumps it to 3NT and you pass, hoping he can stop the red suits.\nSouth plays 3NT. It turns out partner can't stop !Hs either and the defenders reel off 4 !H tricks, then lead a small !D.\nMake a Plan, then click NEXT. [NEXT]\nWinners: !S 2 : !H 0 : !D 2 : !C 3 : Total = 7\nYou need 2 more tricks and you expect to get them from !Cs. This should have been evident while they were leading all those !H winners so you would not have discarded one of the !Cs from your hand. But you also had to be careful not to discard even one of dummy's !Cs, you need all three of them.\nIf the !Cs split 3-2 it wouldn't matter, but if East happens to have !C J x x x then you will need dummy's third !C to make a finesse. You first play your !CA, then lead a small !C to dummy's !CK. West shows out on this !C so you know that East has !C J 9 left. You lead dummy's !C7, finessing East out of the !CJ. \nClick NEXT to see the full deal. [NEXT]\nThis was a very difficult hand.
A97: 100Deals | B97: deal096.html | C97: 96 | D97: BID+NEXT | E97: S:AJ5 H:73 D:8643 C:9532 | F97: S:76 H:JT95 D:972 C:QT74 | G97: S:KQT83 H:K62 D:AK C:AK6 | H97: S:942 H:AQ84 D:QJT5 C:J8 | I97: South | J97: 2C | pass 2D pass 2S | pass 4S pass pass | pass | K97: 4S | L97: South | M97: DQ | N97: You are South and it is your bid. Decide what you would say, then click on BID. [BID 2!C]\nYou have 23 points. You must open 2!C.\nPartner responds 2!D showing 7 or fewer points.\nWhat do you bid? [BID 2!S]\nFollowing partner's negative response you merely bid your suit at the cheapest level.\nYou bid 2!S and partner jumps to 4!S.\nNow what do you say? [BID pass]\nPartner's first response told you he has a weak hand. It didn't suddenly turn into T or 11 points. Partner is merely pulling a "He Who Knows, Goes" bid. He thinks you belong in 4!S.\nSouth plays 4!S. West leads the !DQ.\nMake a Plan, then click NEXT. [NEXT]\nLosers: !S 0 : !H 3 : !D 0 : !C 1 : Total = 4\nIt is possible (but not probable) that !Cs will split 3-3. \nIt is possible (one chance out of two) that East holds the !HA. You could pull trumps, ending in dummy, then lead toward your !HK.\nIt is almost certain that you could ruff your !H loser in dummy, but only if you play a !H at trick two, leading away from your !HK. The defenders will win the !H cheaply and probably play a trump. You win dummy's !SA and play another !H which they also win. They lead a second trump which you win in your hand. You now ruff the last !H with dummy's !SJ, return to your hand, pull trumps and claim.\nClick NEXT to see the full deal. [NEXT]\nIf instead you decide to lead a !S to dummy's !SJ and lead a !H toward your !HK you might go down. West could win the !HA and play a second trump. When you played the next !H West would win again and play a third round of trumps. You would no longer be able to ruff the !H loser.
A98: 100Deals | B98: deal097.html | C98: 97 | D98: BID+NEXT | E98: S:KT4 H:T6 D:753 C:T8643 | F98: S:A952 H:42 D:9864 C:AKJ | G98: S:863 H:AKQJ975 D:AK C:7 | H98: S:QJ7 H:83 D:QJT2 C:Q952 | I98: South | J98: 4H | pass pass pass | K98: 4H | L98: South | M98: DQ | N98: You are South and it is your bid. Decide what you would say, then click on BID. [BID 4!H]\nOne school of thought says to open 2!C with a hand that is within one trick of game, even though the point count is below 22.\nAnother school of thought says to go ahead and bid the game, hoping to keep the opponents away from any competition.\nToday you take the second and bid 4!H.\nSouth plays 4!H. West leads the !DQ.\nMake a Plan, then click NEXT. [NEXT]\nLosers: !S 3 : !H 0 : !D 0 : !C 1 : Total = 4\nYou are going to lose the !C for sure, so you need to find a way to hold the !S losers to 2. The obvious possibility is for West to hold the !SA and you lead through him to make the !SK a winner. That's a 50% possibility.\nBut you can improve on that a little bit. If West holds both the !S Q J you could make a deep finesse of dummy's !ST and East would have to play his !SA to win the trick. And if it didn't work and East won with a lesser !S you would still have time to play toward the !SK.\nWin the !D, pull trumps, lead the !S3 to dummy's !ST. \nClickfor the full deal. [NEXT]\nYou must modify the Plan a little bit. Now your only hope is that West still holds the !SJ. So you win the next trick in your hand and lead a !S toward dummy's !ST. This time West is caught. He plays the !SJ hoping you had a doubleton, but you still have a !S to get to the now high !ST.
A99: 100Deals | B99: deal098.html | C99: 98 | D99: BID+NEXT | E99: S:8 H:A4 D:AK873 C:AT965 | F99: S:JT542 H:K7 D:Q54 C:KJ7 | G99: S:97 H:QJT9653 D:62 C:Q3 | H99: S:AKQ63 H:82 D:JT9 C:842 | I99: South | J99: 3H | pass 4H pass pass | pass | K99: 4H | L99: South | M99: SA | N99: You are South and it is your bid. Decide what you would say, then click on BID. [BID 3!H]\nYou are very weak. But you are also not vulnerable.\nSo with 5 playing tricks you leap to 3!H. Partner raises to 4!H and you pass.\nSouth plays 4!H. West leads !SA, then !H8.\nMake a Plan, then click NEXT. [NEXT]\nLosers: !S 2 : !H 1 : !D 0 : !C 1 : Total = 4\nYou've already lost 1 !S, you can't escape the !C and it looks like the !H is unavoidable also. So that means you can't afford to lose that second !S.\nIf you play dummy's !H4 East will win the !HK and play another !H. You will lose that second !S and go down 1.\nInstead you should rise with dummy's !HA, play !DA, !DK and then a small !D which you ruff. Now play your !S9 and ruff with dummy's last trump.\nClickfor the full deal. [NEXT]\nBut you don't want to get into the habit of doing what is USUALLY good without thinking through the consequences.
A100: 100Deals | B100: deal099.html | C100: 99 | D100: BID+NEXT | E100: S:AJ6 H:Q73 D:Q852 C:762 | F100: S:842 H:AJT64 D:KJT C:53 | G100: S:KT H:852 D:A74 C:AKQ98 | H100: S:Q9753 H:K9 D:963 C:JT4 | I100: South | J100: 1NT | pass 2NT pass 3NT | pass pass pass | K100: 3NT | L100: South | M100: S5 | N100: You are South and it is your bid. Decide what you would say, then click on BID. [BID 1NT]\nWith a balanced, 17 point hand you open 1NT. Partner responds 2NT. What do you bid? [BID 3NT]\nYou were invited to bid 3NT if you have a maximum opener. With 17 points you accept the invitation.\nSouth plays 3NT. West leads !S5. You put on dummy's !S6 and East plays the !S8.\nMake a Plan, then click NEXT. [NEXT]\nWinner count: !S 2 : !H 0 : !D 1 : !C 5 : Total = 8\nThe good news is that they didn't lead a !H. The bad news is that if you give up the lead they probably will. \nAssuming the !Cs behave you need to get one more winner. It's possible you could lead toward dummy's !DQ but even if it works they would probably attack !Hs. Your best chance of getting an extra trick lies in the !S suit.\nIt is almost certain that West holds the !SQ. Of course defenders sometimes don't lead according to the guidelines, but if East had the !SQ he would likely have played it at the first trick. In addition, the Rule of 11 tells you there were 6 cards in the North, East and South hands higher than the !S5. You can account for all of them, so West must have the !SQ. In that case you can assure the contract by winning the first trick with the !SK rather than the !ST. In this way you will be able to gain a trick by finessing West for the !SQ. It's true that if you won with the !ST you would still have both the !SK and !SA remaining, but you wouldn't have the dummy entry you needed.\nClick NEXT to see the full deal. [NEXT]\nNotice how strange this game can be. If your holding was !S K 2 rather than !S K T you would have had no difficulty coming up with the correct play. But the fact that you can win a cheap trick with the !ST tries to lure you into making an inferior play.
A101: 100Deals | B101: deal100.html | C101: 100 | D101: BID+NEXT | E101: S:964 H:K62 D:Q62 C:J753 | F101: S:87 H:T9 D:AKJ73 C:QT62 | G101: S:AKQ53 H:AQ73 D:54 C:A8 | H101: S:JT2 H:J854 D:T98 C:K94 | I101: South | J101: 1S | pass 2S pass 4S | pass pass pass | K101: 4S | L101: South | M101: DT | N101: You are South and it is your bid. Decide what you would say, then click on BID. [BID 1!S]\nYou have a nice hand, but can only open 1!S.\nPartner raises to 2!S. What do you bid? [BID 4!S]\nPartner has 6-10 points, you have 20 points.\nThe math works so you bid 4!S.\nSouth plays 4!S. West leads the !DT, you cover and East plays the three high !Ds.\nMake a Plan, then click NEXT. [NEXT]\nLosers: !S 0 : !H 1 : !D 2 : !C 1 : Total = 4\nTo start with, you ruff the third !D. You cannot avoid the !C loser, so you might think that !Hs must break evenly to give you a fourth !H trick. In fact, there is a chance that you might ruff the fourth !H.\nPlay exactly two rounds of trumps with the !SA and !SK. Then play !HK, !HA and !HQ. If both defenders follow to three leads your fourth !H is good so you pull the last trump. If somebody shows out on the third lead and does not ruff then play your last !H and ruff in dummy. Return to your hand with the !CA and pull trumps.\nClick NEXT to see the full deal. [NEXT]\nBy pulling exactly 2 rounds of trumps first you can also succeed in the case where !Hs split 4-2 and the defender with the doubleton !H also has a doubleton trump.
A102: 100NT | B102: deal01.html | C102: 1 | D102: BID+NEXT | E102: S:75 H:K64 D:KQ74 C:J986 | F102: S:QT3 H:Q95 D:J986 C:A73 | G102: S:A82 H:AT82 D:A3 C:KQT4 | H102: S:KJ964 H:J73 D:T52 C:52 | I102: South | J102: 1NT | pass 2NT pass 3NT | pass pass pass | K102: 3NT | L102: South | M102: S6 | N102: The bidding has gone as shown. Decide what you would say, then click on BID above. [BID 3NT]\nPartner's 2NT bid invites you to bid game if you have a maximum hand. Your 17 points is certainly a maximum so you bid 3NT.\nClick NEXT to continue. [NEXT]\nWill you take your !SA immediately? or at trick 2? or trick 3?\nMake a Plan, then click NEXT. [NEXT]\nYou need 3 more tricks, and they must come from !Cs. So you must drive out the !CA. The problem is that when the defenders win the !CA they may also take 4 !S tricks.\nWhile you cannot guarantee the contract you can at least give yourself a better chance by holding up your !SA on the first trick, and also on East's !S continuation. You win the third !S with your !SA. [NEXT]\nNow you drive out the !CA. There are four possibilities:West may win the !CA and cash two more !Ss, down 1. West may win the !CA and cash just one !Ss, you make it. East may win the !CA and have a fourth !S to lead, you make it. East may win the !CA and be out of !Ss, you make it.\nClick NEXT to see the full deal. [NEXT]\nIf you win the first or second !S trick you will fail. When you attack !Cs, East will win the !CA and play a !S.\nHolding up twice can never hurt, and in this case it is the only way to make the contract.
A103: 100NT | B103: deal02.html | C103: 2 | D103: BID+NEXT+ROTATE | E103: S:J98642 H:4 D:K653 C:83 | F103: S:AQ3 H:K753 D:T8 C:KT62 | G103: S:T5 H:AQ62 D:AQ4 C:AJ74 | H103: S:K7 H:JT98 D:J972 C:Q95 | I103: North | J103: 1NT | pass 2H pass 2S | pass pass pass | K103: 2S | L103: North | M103: C2 | N103: The bidding has gone as shown. Decide what you would say, then click on BID above. [BID 2!H]\nIn the pre-transfer days you would have bid 2!S with this hand and partner would have passed. Now you make partner bid the !Ss first by saying 2!H. Partner dutifully replies 2!S. What do you say? [BID pass]\nIn the pre-transfer days you would have bid 2!S with this hand and partner would have passed. Now you make partner bid the !Ss first by saying 2!H. Partner dutifully replies 2!S. What do you say?\nYou say pass.\nClick NEXT to continue. [NEXT]\nThe contract would be 2!S played by North.\nTo make South the declarer click ROTATE. [ROTATE]\nSouth plays 2!S. West leads the !C2. East plays the !CQ which you take with your !CA.\nMake a Plan, then click NEXT. [NEXT]\nCount losers in the long-trump hand, (dummy this time).\nYou can make the contract if you just force out their big trumps. But there is another tempting possibility. You could enter dummy with the !DK and play the !H4, finessing East for the !HK. If the finesse is successful you could then discard dummy's !C loser on the !HA.\nShould you or shouldn't you? [NEXT]\nThe reward for this play would be an overtrick. The price of failure would be going down in a cold contract. So obviously, at rubber bridge, you would be foolish to take such a risk. Playing Duplicate though, you might consider it. But let's say you decide to play safe. [NEXT]\nWin the !CA and play a trump. As soon as you get in play another trump. The defenders will no doubt take their !C winner when they get in. East will no doubt win one of those high trump tricks, and he MAY lead a !H when he gets in. There you will be, trying to decide again whether to finesse . . .\nClick for the full deal. [NEXT]\nAs you see, the !HK is in the wrong place this time, but might be right the next time.\nUsually you should not risk your contract for the sake of an overtrick.
A104: 100NT | B104: deal03.html | C104: 3 | D104: BID+NEXT | E104: S:J4 H:A985 D:JT73 C:K82 | F104: S:A92 H:JT73 D:A64 C:J63 | G104: S:K65 H:KQ D:KQ82 C:AT74 | H104: S:QT873 H:642 D:95 C:Q95 | I104: South | J104: 1NT | pass 2C pass 2D | pass 2NT pass 3NT | pass pass pass | K104: 3NT | L104: South | M104: S7 | N104: The bidding has gone as shown. Decide what you would say, then click on BID above. [BID 2!D]\nPartner's 2!C is Stayman convention. With no 4-card Major suit your response is 2!D. Partner now bids 2NT. What do you say? [BID 3NT]\nPartner's 2!C is Stayman convention. With no 4-card Major suit your response is 2!D. Partner now bids 2NT. What do you say?\nThe 2NT bid is invitational, asking you to bid game with a maximum, pass with a minimum. You have 17 points so you bid 3NT.\nClick NEXT to continue. [NEXT]\nYou put on dummy's !SJ, but East wins the !SA then continues with the !S9. Do you play your !SK now?\nMake a Plan, then click NEXT. [NEXT]\nYou need 3 more tricks, and they must come from !Ds. So you must drive out the !DA. The problem is that when the defenders win the !DA they may also take 4 !S tricks.\nThis is another case where you should hold up. Allow EW to win the second trick and take your !SK only at trick #3. [NEXT]\nNow you drive out the !DA. If West has it and also started with 5 !Ss you will go down. But if East has the !DA you will make the contract no matter how !Ss split.\nClick NEXT to see the full deal. [NEXT]\nIf you win the second !S East will still have a !S when he wins the !DA.\nBut if you hold up your !SK East will have no !S to put his partner in with.
A105: 100NT | B105: deal04.html | C105: 4 | D105: BID+NEXT+ROTATE | E105: S:Q9 H:843 D:KJT82 C:JT4 | F105: S:J743 H:KJ95 D:Q95 C:85 | G105: S:K85 H:A2 D:A73 C:AKQ72 | H105: S:AT62 H:QT76 D:64 C:963 | I105: North | J105: 2NT | pass 3NT pass pass | pass | K105: 3NT | L105: North | M105: H5 | N105: The bidding has gone as shown. Decide what you would say, then click on BID above. [BID 3NT]\nEven if you wanted to show your !D suit how would you do it? If you bid 3!D it would be a transfer and if you bid 4!D you would have bypassed 3NT, your probable best contract.\nBut you didn't want to bid them anyway, you just wanted to bid 3NT, right?\nClick NEXT to continue. [NEXT]\nThe contract would be 3NT played by North.\nTo make South the declarer click ROTATE. [ROTATE]\nWest leads !H5, East plays the !HQ.\nThe first thing you need to decide is whether to hold up on the !H.\nMake a Plan, then click NEXT. [NEXT]\nFirst decide the holdup question. West led the !H5 and you can see the !H4, !H3 and !H2. Assuming West led fourth down he must have only a 4-card suit since there are no cards he could have lower than the !H5. With !Hs splitting 4-4 a holdup would do no good, and isn't necessary anyway.\nSo take the !HA. Then what? [NEXT]\nYou COULD try the !D finesse. Even if it loses it would establish several !D winners. However, if the defenders win just 1 !D trick they will quickly grab their 3 !H tricks and their !SA and put you down 1. [NEXT]\nThis is why it is important to make a Plan which includes a Winner count. You need just one additional winner and all you have to do to get it is play a !S honor.\nClickfor the full deal. [NEXT]\nWhen you can see all four hands, including the location of the !DQ, it kind of makes you wished you had finessed and gotten all those overtricks.\nGood Bridge players like to take tricks, but they are not greedy.
A106: 100NT | B106: deal05.html | C106: 5 | D106: BID+NEXT | E106: S:KJ853 H:AJ42 D:5 C:A64 | F106: S:96 H:QT83 D:J962 C:QJ3 | G106: S:AQT2 H:K7 D:KQ73 C:K75 | H106: S:74 H:965 D:AT84 C:T982 | I106: South | J106: 1NT | pass 2H pass 3S | pass 4NT pass 5D | pass 6S pass pass | pass | K106: 6S | L106: South | M106: CT | N106: The bidding has gone as shown. Decide what you would say, then click on BID above. [BID 3!S]\nPartner's 2!H bid is a transfer; he expects you to bid 2!S. However, with such great !S support and an outside doubleton your hand now revalues to 18 points - more than an opening 1NT. You indicate this with a jump to 3!S. This is called a "Super-Accept". Partner now bids 4NT. What do you answer? [BID 5!D]\nPartner's 2!H bid is a transfer; he expects you to bid 2!S. However, with such great !S support and an outside doubleton your hand now revalues to 18 points - more than an opening 1NT. You indicate this with a jump to 3!S. This is called a "Super-Accept". Partner now bids 4NT. What do you answer?\nBlackwood, and with one Ace you answer 5!D. Partner bids 6!S and everybody passes.\nClick NEXT to continue. [NEXT]\nIt won't matter where you take it, but assume you win in your hand.\nMake a Plan, then click NEXT. [NEXT]\nSince the !D loser is a sure thing you will need to find somewhere to discard a !C. There are three possibilities:Finesse West for the !HQ. (50% chance)Try to drop the !HQ by ruffing the third round. (also about 50%)Establish a !D honor. (T0% certain) [NEXT]\nFirst pull trumps, ending in dummy. It takes two rounds. Next play the !D5 toward your !DQ. West wins this and plays another !C. Win the !C, come to your hand with the !HK, then play your good !DQ, discarding dummy's losing !C.\nYou will need to ruff two !Hs in your hand, but the rest of the tricks are yours.\nClick NEXT to see all four hands. [NEXT]\nIf they had been 3-1 you would have had to leave the last trump undrawn until after you had ruffed two !Hs in your hand.
A107: 100NT | B107: deal06.html | C107: 6 | D107: BID+NEXT+ROTATE | E107: S:AJ6 H:QJ9752 D:642 C:8 | F107: S:Q853 H:6 D:KQJ9 C:A753 | G107: S:K4 H:KT43 D:A75 C:KQJ2 | H107: S:T972 H:A8 D:T83 C:T964 | I107: North | J107: 1NT | pass 2D pass 2H | pass 4H pass pass | pass | K107: 4H | L107: North | M107: DK | N107: The bidding has gone as shown. Decide what you would say, then click on BID above. [BID 2!D]\nWith 10 points and a 6-card !H suit you want to transfer. You say 2!D and partner bids 2!H. What do you bid now? [BID 4!H]\nWith 10 points and a 6-card !H suit you want to transfer. You say 2!D and partner bids 2!H. What do you bid now?\nYou know you want to play in !Hs since partner will have at least 2 of them. Your problem is whether to merely invite with 3!H or go ahead and bid the game. Since partner has either 15, 16 or 17 points you should probably just bid 4!H. The worst thing that could happen is that partner would be playing game with only 25 points.\nClick NEXT to continue. [NEXT]\nThe contract would be 4!H played by North.\nTo make South the declarer click ROTATE. [ROTATE]\nSouth plays 4!H. West leads the !DK. Do you hold up or not?\nMake a Plan, then click NEXT. [NEXT]\nThere is no reason to hold up. Besides, you have bigger problems to deal with.\nAfter you take the !DA at trick one you have four fast losers staring you in the face the instant you lose the lead. So do you pull trumps now? [NEXT]\nNo, you dare not touch trumps yet - remember those 4 fast losers. \nYou cannot avoid the !HA and !CA, so you must get rid of one of the !D losers before you play trumps. [NEXT]\nWin the !DA, play the !SK, then finesse the !SJ. If the finesse works discard a !D on the !SA, then pull trumps. If the finesse fails you will go down 2 instead of 1.\nClick NEXT to see whether you made it or went down 2. [NEXT]\nWhen the cards MUST lie in a particular way for the contract to be makeable, just assume that's the way they lie and go for it.
A108: 100NT | B108: deal07.html | C108: 7 | D108: BID+NEXT | E108: S:743 H:AQ72 D:753 C:K84 | F108: S:A6 H:63 D:QT984 C:QJT6 | G108: S:QJT5 H:K54 D:AK6 C:A52 | H108: S:K982 H:JT98 D:J2 C:973 | I108: South | J108: 1NT | pass 2C pass 2S | pass 2NT pass 3NT | pass pass pass | K108: 3NT | L108: South | M108: HJ | N108: The bidding has gone as shown. Decide what you would say, then click on BID above. [BID 2!S]\nIn response to partner's Stayman bid you show your 4-card !S suit. Partner now bids 2NT. What do you say? [BID 3NT]\nIn response to partners Stayman bid you show your 4-card !S suit. Partner now bids 2NT. What do you say?\nYou may disagree with the Stayman bid on 3-4-3-3 distribution. In any case, 2NT is invitational, so with 17 points you say 3NT.\nClick NEXT to continue. [NEXT]\nMake a Plan, then click NEXT. [NEXT]\nWest's !HJ lead probably means !Hs won't be 3-3, so you will need to get 2 !S tricks.\nSuppose you win the first trick and plunk down the !SQ. If East wins with a doubleton !S honor you will only be able to win 1 !S since West will sit there with !S A 9 or !S K 9 behind your !S J T. [NEXT]\nInstead, win the first trick in dummy and play a small !S toward the !S Q J T. East will play low and West must take his !S honor. But you can win his return, enter dummy and play another !S toward your hand. If you are lucky, East will be forced to play an honor and you can toss your !S5.\nto see if you were lucky. [NEXT]\nIt only fails if West holds 4 or more !Ss headed by A K.
... A200: 100NT | B200: deal99.html | C200: 99 | D200: BID+NEXT+ROTATE | E200: S:K5 H:Q86 D:AQ73 C:KQ86 | F200: S:Q7 H:954 D:T952 C:JT97 | G200: S:A9862 H:KJT72 D:6 C:42 | H200: S:JT43 H:A3 D:KJ84 C:A53 | I200: South | J200: 1NT pass 2H | pass 2S pass 3H | pass 4H pass pass | pass | K200: 4H | L200: North | M200: CJ | N200: The bidding has gone as shown. Decide what you would say, then click on BID above. [BID 2!S]\nPartner's bid is a transfer asking you to bid 2!S, so you do. Partner now bids 3!H; what do you bid next? [BID 4!H]\nPartner's bid is a transfer asking you to bid 2!S, so you do. Partner now bids 3!H; what do you bid next?\nPartner is showing 5-5 in the Majors, with at least invitational strength. It's a close thing, but you decide to accept the invitation and bid 4!H.\nClick NEXT to continue. [NEXT]\nThe contract would be 4!H played by North.\nTo make South the declarer click ROTATE. [ROTATE]\nSouth plays 4!H. West leads the !CJ. You play the !CQ. East wins with the !CA and plays the !HA then the !H3.\nMake a Plan, then click NEXT. [NEXT]\nEast trump play was good defense; it has prevented you from ruffing 2 !Ss in dummy. Even so your best plan will be to establish the !S suit.\nSo you next play !SK, !SA, then ruff a !S with dummy's !HQ. West does not follow to the third !S. [NEXT]\nNext play !DA and get to your hand by ruffing a !D. Pull the last trump, then give up a !S to East. Win his return, (by ruffing if necessary) and take your established !S winner and dummy's !CK. \nClick for the complete Deal. [NEXT]\nIt would have done you no good at all.\nIf it worked, all you could do would be to discard your fifth !S; but that was the !S that turned out to be a winner! \nIt was the fourth !S that was a loser, and you couldn't get rid of that one.
A201: 100NT | B201: dealc.html | D201: BID+NEXT+ROTATE | E201: S:A964 H:8762 D:K75 C:K6 | F201: S:JT7 H:J5 D:QJ92 C:JT43 | G201: S:K5 H:A943 D:A64 C:A982 | H201: S:Q832 H:KQT D:T83 C:Q75 | I201: North | J201: 1NT | pass 2C pass 2H | pass 4H pass pass | pass | K201: 4H | L201: North | M201: DQ | N201: The bidding has gone as shown. Decide what you would say, then click on BID above. [BID 2!C]\nWith 10 points and two 4-card Majors you bid 2!C Stayman. Partner says 2!H; what do you bid next? [BID 4!H]\nWith 10 points and two 4-card Majors you bid 2!C Stayman. Partner says 2!H; what do you bid next?\nNow you add a point for your doubleton, get to 11 points, and bid 4!H.\nClick NEXT to continue. [NEXT]\nThe contract would be 4!H played by North.\nTo make South the declarer click ROTATE. [ROTATE]\nSouth plays 4!H. West leads the !DQ. Win the !DQ in either hand. Lets say you win with your !DA.\nMake a Plan, then click NEXT. [NEXT]\n*Don't get overconfident with this loser list. It assumes that trumps break 3-2, (if they don't you cannot make it), and also assumes you will be able to cross-ruff 4 small black cards.\nCross-ruffing those 4 losers could be a problem. You can't afford to get over-ruffed so it would be nice if you could pull some trumps before you start the cross-ruff. But you must make sure that only two rounds of trumps get pulled, otherwise you won't have the trumps for the cross-ruff. [NEXT]\nIt is actually simple to make sure exactly two rounds of trumps are drawn. At trick 2 just duck a !H in each hand. An opponent will win this, but you can take the next trick, (probably a !D), and then pull a second round of trumps with your !HA. Then leave the trumps alone and play your two black A K's, then start cross-ruffing with your 4 tiny trumps. The defender with the master trump can over-ruff when he can, and can even cash a !D. But that's all he can do so you will make your game. \nClick for the complete Deal. [NEXT]\nEast would have won the second one, and if he had then continued !Ds you would have made the contract. \nBut if he was a good enough defender to pull a THIRD round of trumps, getting 2 for the price of 1 value, you would have been defeated.
A202: 2Club | B202: deal01.html | C202: 1 | D202: BID | E202: S:Q65 H:864 D:KQ86 C:T87 | F202: S:J94 H:QJ72 D:T973 C:62 | G202: S:AK82 H:AK3 D:A4 C:KQ94 | H202: S:T73 H:T95 D:J52 C:AJ53 | I202: South | J202: 2C | pass 2D pass 2NT | pass 3NT pass pass | pass | K202: 3NT | L202: South | N202: You dealt this hand. Decide what you would bid, then click on BID above. [BID 2!C]\n\nWith 23 points you naturally open 2!C. Partner responds 2!D. What do you bid next? [BID 2NT]\n\nYou have 23 points and no 5-card suit. Since your hand is balanced you bid 2NT. Partner raises to 3NT and you pass.
A203: 2Club | B203: deal02.html | C203: 2 | D203: BID | E203: S:KQ5 H:AK6 D:AK92 C:AT8 | F203: S:A94 H:JT72 D:JT73 C:62 | G203: S:T872 H:Q53 D:864 C:974 | H203: S:J63 H:984 D:Q5 C:KQJ53 | I203: North | J203: 2C pass 2D | pass 2NT pass pass | pass | K203: 2NT | L203: North | N203: The bidding has gone as shown. Decide what you would bid, then click on BID above. [BID 2!D]\n\nWith only 2 points you make a Negative 2!D response to partner's 2!C opener. He now bids 2NT. What is your bid? [BID pass]\n\nThis isn't as clear-cut a decision as you might think at first. Partner is showing 22-24 points, and even though you only have 2 points it is possible that the partnership total could be 26. The thing that should convince you to pass is that a 24-2 point split doesn't play nearly as well as say a 13-13 split would. Lack of transportation would likely kill any chance of 3NT (or 4!S). So you pass.
A204: 2Club | B204: deal03.html | C204: 3 | D204: BID | E204: S:Q65 H:864 D:Q986 C:T87 | F204: S:J94 H:QJ72 D:T753 C:62 | G204: S:AK82 H:AK3 D:AK C:KQ94 | H204: S:T73 H:T95 D:J42 C:AJ53 | I204: South | J204: 2C | pass 2D pass 3NT | pass pass pass | K204: 3NT | L204: South | N204: You dealt this hand. Decide what you would bid, then click on BID above. [BID 2!C]\n\nWith 26 points you naturally open 2!C. Partner responds 2!D. What do you bid next? [BID 3NT]\n\nYou have 26 points and no 5-card suit. Since your hand is balanced you bid 3NT. Everybody passes.
A205: 2Club | B205: deal04.html | C205: 4 | D205: BID | E205: S:KQ5 H:AK6 D:AK92 C:AT8 | F205: S:A74 H:JT72 D:JT73 C:62 | G205: S:JT82 H:Q53 D:864 C:J94 | H205: S:963 H:984 D:Q5 C:KQ753 | I205: North | J205: 2C pass 2D | pass 2NT pass 3NT | pass pass pass | K205: 3NT | L205: North | N205: The bidding has gone as shown. Decide what you would bid, then click on BID above. [BID 2!D]\n\nWith only 4 points you make a Negative 2!D response to partner's 2!C opener. He now bids 2NT. What is your bid? [BID 3NT]\n\nTrue, 4 points isn't much. But added to partner's 22-24 it becomes enough for a game. Your problem isn't whether to bid to the game or not, (you definitely will), but whether you should use Stayman to find out if there is a 4-4 !S fit. You decide not to do this because your 4-3-3-3 distribution removes the possibility of you getting any ruffs. So you bid 3NT.
A206: 2Club | B206: deal05.html | C206: 5 | D206: BID | E206: S:K873 H:92 D:J8742 C:T3 | F206: S:AQ962 H:T D:T63 C:K986 | G206: S: H:AKQJ8643 D:A5 C:QJ4 | H206: S:JT54 H:75 D:KQ9 C:A752 | I206: South | J206: 2C | pass 2D pass 2H | pass 2NT pass 4H | pass pass pass | K206: 4H | L206: South | N206: You dealt this hand. Decide what you would bid, then click on BID above. [BID 2!C]\n\nYou only have 20 points, but you have 9 playing tricks. You have two choices, open 4!H or open 2!C. Usually 4!H would show a slightly weaker hand than this, so you bid 2!C. Partner responds 2!D. What do you bid next? [BID 2!H]\n\nOf course you bid your 8-card suit. But no jumping, just bid 2!H. Partner now says 2NT. What do you bid next? [BID 4!H]\n\nPartner has between 3 and 7 points. Somewhere in those points might be the one trick you need, but you don't have any scientific way of finding out. So just bid 4!H and hope.(There it is, the !CT.)
A207: 2Club | B207: deal06.html | C207: 6 | D207: BID | E207: S:AK4 H:AQT86 D:K2 C:KQT | F207: S:QJ9 H:J974 D:83 C:J843 | G207: S:875 H:K3 D:QJT94 C:752 | H207: S:T632 H:52 D:A765 C:A96 | I207: North | J207: 2C pass 2D | pass 2H pass 3D | pass 3NT pass pass | pass | K207: 3NT | L207: North | N207: The bidding has gone as shown. Decide what you would bid, then click on BID above. [BID 2!D]\n\nWith 7 points you must bid a Negative 2!D. Partner now bids 2!H. What is your bid? [BID 3!D]\n\nFor someone who made an initial Negative response you have quite a good hand. You can't support partner's !Hs (yet) but you consider jumping to 3NT. All in all it is better to just describe your hand with a 3!D bid, then wait and see what partner says. You don't have to wait long since he bids 3NT which you pass.
A208: 2Club | B208: deal07.html | C208: 7 | D208: BID | E208: S:K65 H:T864 D:92 C:T873 | F208: S:T72 H:KQ72 D:JT85 C:62 | G208: S:AQJ83 H:3 D:KQ7 C:AKQ9 | H208: S:94 H:AJ95 D:A643 C:J54 | I208: South | J208: 2C | pass 2D pass 2S | pass 4S pass pass | pass | K208: 4S | L208: South | N208: You dealt this hand. Decide what you would bid, then click on BID above. [BID 2!C]\n\nWith 22 points you should open 2!C. Partner responds 2!D. What do you bid next? [BID 2!S]\n\nYou have 22 points and 5-card Major suit. Your rebid is therefore 2!S. Partner raises to 4!S. His jump to game shows a weaker hand than a 3!S bid would so you pass.
A209: 2Club | B209: deal08.html | C209: 8 | D209: BID | E209: S:AQ H:AK75 D:Q84 C:AKJT | F209: S:J942 H:94 D:AJ973 C:62 | G209: S:K875 H:QJT3 D:T5 C:973 | H209: S:T63 H:862 D:K62 C:Q854 | I209: North | J209: 2C pass 2D | pass 2NT pass 3C | pass 3H pass 4H | pass pass pass | K209: 4H | L209: North | N209: The bidding has gone as shown. Decide what you would bid, then click on BID above. [BID 2!D]\n\nYou have 6 points and bid a Negative 2!D. Partner now bids 2NT. What is your bid? [BID 3!C]\n\nPartner has a balanced 22-24 points. With your 6 you want to be in game, but which game; 3NT, 4!H or 4!S? You can't answer that question unless you know if partner has a 4-card Major suit. So you bid 3!C, which is Stayman in this case. Partner replies 3!H. What do you say? [BID 4!H]\n\nKnowing of the 4-4 fit you bid 4!H. By the way: Partner knew your 3!C bid was not the Second Negative because you don't use Second Negative following a 2NT rebid, you just pass.
A210: 2Club | B210: deal09.html | C210: 9 | D210: BID | E210: S:J943 H:96 D:9863 C:A82 | F210: S:Q862 H:A52 D:Q752 C:63 | G210: S:AK H:KQJT4 D:AJT C:KJ9 | H210: S:T75 H:873 D:K4 C:QT754 | I210: South | J210: 2C | pass 2D pass 2H | pass 2NT pass 3NT | pass pass pass | K210: 3NT | L210: North | N210: You dealt this hand. Decide what you would bid, then click on BID above. [BID 2!C]\n\nWith 23 points you open 2!C. Partner responds 2!D. What do you bid next? [BID 2!H]\n\nYou bid your 5-card !H suit. Partner says 2NT. What do you bid now? [BID 3NT]\n\nPartner's 2NT shows scattered values and fewer than 3 !Hs. He has 3 or more points or he would have bid the Double Negative. So you say 3NT.
A211: 2Club | B211: deal10.html | C211: 10 | D211: BID | E211: S:AK8 H:KQT D:KQJ2 C:AT4 | F211: S:6543 H:754 D:A8 C:9752 | G211: S:JT7 H:A96 D:T95 C:KQJ3 | H211: S:Q92 H:J832 D:7643 C:86 | I211: North | J211: 2C pass 2NT | pass 3NT pass 6NT | pass pass pass | K211: 6NT | L211: South | N211: The bidding has gone as shown. Decide what you would bid, then click on BID above. [BID 2NT]\n\nYou have 11 points and partner opens 2!C. Wow!You answer 2NT and he bids 3NT. What is your next bid? [BID 6NT]\n\nHmmm, 22-24 balanced, plus 11 balanced equals 33-35 balanced. It makes you think a jump to 6NT would work out great. Just do it.
A212: 2Club | B212: deal11.html | C212: 11 | D212: BID | E212: S:AQT64 H:AQ85 D:Q7 C:AK | F212: S:K3 H:KT92 D:KT952 C:83 | G212: S:9875 H:64 D:863 C:J752 | H212: S:J2 H:J73 D:AJ4 C:QT964 | I212: North | J212: 2C pass 2D | pass 2S pass 3C | pass 3H pass 3S | pass pass pass | K212: 3S | L212: North | N212: The bidding has gone as shown. Decide what you would bid, then click on BID above. [BID 2!D]\n\nWith just 1 Jack you bid a Negative 2!D. Partner now bids 2!S. What is your bid? [BID 3!C]\n\nPartner's bid of a suit is absolutely forcing, no matter how you feel about it. But now is the time you tell him you have fewer than 3 points by using the Second Negative. You bid 3!C. Partner now says 3!H. What do you say? [BID 3!S]\n\nNo, you still may not pass. First, because partner's bid of a new suit is forcing. Second, because even if you were not forced you prefer his first suit. So you bid 3!S and he passes.
A213: 2Club | B213: deal12.html | C213: 12 | D213: BID | E213: S:A5 H:A6 D:K7 C:AKQJT63 | F213: S:KJ942 H:J943 D:AJ2 C:4 | G213: S:763 H:852 D:9543 C:872 | H213: S:QT8 H:KQT7 D:QT86 C:95 | I213: North | J213: 2C pass 2D | pass 3C pass 3D | pass 3NT pass pass | pass | K213: 3NT | L213: North | N213: The bidding has gone as shown. Decide what you would bid, then click on BID above. [BID 2!D]\n\nWith a true Yarborough you qualify to respond a Negative 2!D. Partner now bids 3!C. What is your bid? [BID 3!D]\n\nYou now inform partner of your disaster hand by using the Second Negative. Since his suit is !Cs the Second Negative is 3!D. Partner now says 3NT. What do you say? [BID pass]\n\nYou definitely pass. Good thing he has 9 cold tricks in his hand!
... A221: 2Club | B221: deal20.html | C221: 20 | D221: BID | E221: S:AKQ75 H:A6 D:AQ7 C:KQ3 | F221: S:J94 H:984 D:K8542 C:72 | G221: S:63 H:KQJT2 D:T96 C:984 | H221: S:T82 H:753 D:J3 C:AJT65 | I221: North | J221: 2C pass 2D | pass 2S pass 3H | pass 3NT pass pass | pass | K221: 3NT | L221: North | N221: The bidding has gone as shown. Decide what you would bid, then click on BID above. [BID 2!D]\n\nWith one more point you could have made a positive response. Instead, you bid 2!D. Partner now bids 2!S. What is your bid? [BID 3!H]\n\nNot being in love with partner's !Ss, you have enough strength to now bid 3!H. Partner replies 3NT. What do you say? [BID pass]\n\nWhen you have nothing more to say, you pass.
A222: 2over1 | B222: deal01.html | C222: 1 | E222: S:QT5 H:KQJT5 D:74 C:AQ6 | F222: S:A962 H:963 D:QJ82 C:72 | G222: S:J84 H:A2 D:KT963 C:KJ4 | H222: S:K73 H:874 D:A5 C:T9853 | I222: North | J222: 1H pass 2D | pass 2NT pass 3NT | pass pass pass | K222: 3NT | L222: North | N222: After North's 1!H opening South counts 12 HCP plus one length point for the fifth !D. That is enough for a 2/1 response so South says 2!D.\nThe partnership is now forced to reach game so North bids 2NT. This describes a balanced hand with exactly 5 !Hs and no 4-card !S suit.\nSouth is happy to play in Notrump, and with no extra strength above the 13 points already promised, uses Quick Arrival and bids 3NT. North passes and a reasonable game contract is reached.\nNotice that you would bid this hand the same way whether or not you play 2/1.
A223: 2over1 | B223: deal02.html | C223: 2 | E223: S:65 H:KQJ843 D:A5 C:Q63 | F223: S:AT732 H:75 D:J872 C:82 | G223: S:KJ8 H:A2 D:KT963 C:KJ4 | H223: S:Q94 H:T96 D:Q4 C:AT975 | I223: North | J223: 1H pass 2D | pass 2H pass 3H | pass 4H pass pass | pass | K223: 4H | L223: North | N223: North opens 1!H and South, with 16 points, responds 2!D, forcing the partnership to game.\nNorth has a minimum strength hand, but with a 6-card suit he rebids 2!H.\nOpposite North's 6-card suit, South's doubleton is adequate support. If South had a minimum for her 2/1 response she might just jump to 4!H to show no interest in slam. With a little extra she bids 3!H since she knows the bidding cannot stop until game is reached. From South's perspective North might have a big hand; his 2-level rebid shows suit length but does not say anything about strength. This is one of the beauties of 2/1, the bidding can be kept low while you look for the best place to play. However, this time North merely bids the game and South passes.\nThe hand would have been bid the same with or without 2/1.
A224: 2over1 | B224: deal03.html | C224: 3 | E224: S:K5 H:KQJ743 D:75 C:AK4 | F224: S:AJ932 H:T6 D:T2 C:J952 | G224: S:Q6 H:A82 D:AKQ63 C:763 | H224: S:T874 H:95 D:J984 C:QT8 | I224: North | J224: 1H pass 2D | pass 2H pass 3H | pass 4C pass 4D | pass 4NT pass 5H | pass 6H pass pass | K224: 6H | L224: North | N224: With 16+ points and 3 !Hs, South will insist on a !H game at a minimum. But there is no need to start making jump bids, she starts with a simple 2!D bid. North also refrains from a jump, and rebids 2!H to show the 6-card suit.\nSouth now says 3!H to set the trump suit. At this point North reveals some slam interest, making a control-showing bid of 4!C. South continues the process, and bids 4!D, showing the !DA.\nNorth has heard enough. He bids 4NT, and when South admits to two Aces he bids the slam.
A225: 2over1 | B225: deal04.html | C225: 4 | E225: S:AKJ865 H:43 D:75 C:K63 | F225: S:9743 H:K D:AKQJ84 C:Q8 | G225: S:Q H:A9865 D:962 C:A742 | H225: S:T2 H:QJT72 D:T3 C:JT95 | I225: North | J225: 1S 2D 2H | pass 2S pass pass | pass | K225: 2S | L225: North | N225: North has a minimum 1!S opening bid. After East's 2!D overcall both North and South know that the 2/1 Game Force in no longer on. South can therefore bid 2!H, showing at least 11 points. This bid is forcing on North for 1 round, but not forcing to game.\nNorth next rebids his !Ss, promising a 6-card suit, but also indicating a minimum strength hand! Since the Game Force is not on, North would have to make a jump bid to show extra strength.\nSouth has nothing further to say so the partnership arrives in a safe contract.
A226: 2over1 | B226: deal05.html | C226: 5 | E226: S:KJ965 H:AK843 D:75 C:4 | F226: S:A83 H:J92 D:Q9842 C:72 | G226: S:Q4 H:QT7 D:AJ6 C:AT986 | H226: S:T72 H:65 D:KT3 C:KQJ53 | I226: North | J226: 1S pass 2C | pass 2H pass 2NT | pass 3H pass 4H | pass pass pass | K226: 4H | L226: North | N226: North opens 1!S, the higher ranking of the two 5-card suits.\nSouth, with 14 points, responds 2!C, forcing the partnership to game.\nNorth now bids his !H suit.\nAt this point South figures North for 5 !Ss and 4 !Hs. South cannot support either of North's Majors, but with a good stopper in the fourth suit bids 2NT. The game force is still on and North may not pass this bid.\nNorth bids 3!H, indicating that this is also a 5-card suit. Now South can bid the !H game, knowing there is an 8-card fit.
A227: 2over1 | B227: deal06.html | C227: 6 | E227: S:65 H:AQ953 D:KQ63 C:Q9 | F227: S:KQ8 H:864 D:J7 C:KT643 | G227: S:AJT74 H:KT7 D:A95 C:72 | H227: S:932 H:J2 D:T842 C:AJ85 | I227: East | J227: pass 1S | pass 2H pass 3H | pass 4H pass pass | pass | K227: 4H | L227: North | N227: South opens 1!S and North, with 14 points, responds 2!H. Note that North is not permitted to make this bid without a 5-card or longer !H suit.\nSouth, knowing that North has 5, bids 3!H to confirm the trump suit.\nNorth has a minimum strength hand with no slam aspirations, so he uses Fast Arrival and bids 4!H. South is also satisfied to just play at game.\n2/1 is a good bidding method, and here, 4!H is a good contract. But you can see that it is not a laydown - there is no bidding system that will always reach T0% contracts. In this hand a 3-3 !D split will provide the Tth trick, or if that fails, taking 2 !S finesses provides a 75% chance of success.
A228: 2over1 | B228: deal07.html | C228: 7 | E228: S:AK9652 H:T983 D:4 C:A8 | F228: S:QT4 H:QJ2 D:QT983 C:52 | G228: S:7 H:AK75 D:K762 C:KQT6 | H228: S:J83 H:64 D:AJ5 C:J9743 | I228: North | J228: 1S pass 2C | pass 2H pass 3H | pass 4H pass pass | pass | K228: 4H | L228: North | N228: North has 13 points and naturally opens 1!S.\nSouth, with 15 points, would bid 2!H in standard bidding, but with 2/1 this promises a 5-card suit. So instead, South responds 2!C, forcing the partnership to game. Note that holding two 4-card minors South bids them up-the-line, just as in standard bidding.\nNorth has a nice 6-card !S suit, so you might think he would rebid them. But Opener's first responsibility with his second bid is to show a 4-card Major if he has one. This isn't much of a suit, but North still bids 2!H.\nYou can see why it is important for Opener to show a 4-card Major. Since South couldn't bid !Hs in her first response the fit would have been lost if North had not mentioned the suit. South now confirms the trump suit with a 3!H bid, and North shows his minimum by just bidding the game.
A229: 2over1 | B229: deal08.html | C229: 8 | E229: S:AK92 H:AQ983 D:85 C:86 | F229: S:QJ6 H:T762 D:6 C:AJ532 | G229: S:875 H:K4 D:AQJT7 C:K97 | H229: S:T43 H:J5 D:K9432 C:QT4 | I229: North | J229: 1H pass 2D | pass 2S pass 2NT | pass 3NT pass pass | pass | K229: 3NT | L229: South | N229: North opens 1!H, his 5-card Major. South, with 14 points, naturally responds 2!D, forcing the partnership to game.\nNorth next bids 2!S, showing the other Major suit. In standard bidding North would not be able to bid the !Ss since that would be a Reverse and North is far too weak to Reverse. But after a 2/1 Response the concept of a Reverse does not apply, and the priority of showing a 4-card Major certainly does apply.\nSouth assumes North to be 4-5 in the Majors, so she cannot support either. She bids 2NT. If North actually has 6 !Hs (or 5 !Ss) he will rebid the suit. South's 2NT bid guarantees a stopper in the fourth suit.\nNorth does not have either 6 !Hs or 5 !Ss so he just bids 3NT. Notice that North never once considered the possibility of passing what might be a misfit - the initial 2/1 response unconditionally forced the partnership to reach a game somewhere.
A230: 2over1 | B230: deal09.html | C230: 9 | E230: S:A9742 H:A983 D:K6 C:Q7 | F230: S:QT53 H:Q54 D:AJ32 C:95 | G230: S:K8 H:JT7 D:975 C:AKJ62 | H230: S:J6 H:K62 D:QT84 C:T843 | I230: North | J230: 1S pass 2C | pass 2H pass 3D | pass 3NT pass pass | pass | K230: 3NT | L230: North | N230: North opens 1!S, his 5-card Major. South, with 14 points, responds 2!C, a 2/1 force to game.\nNorth next bids 2!H, showing the other Major suit.\nSouth assumes North to be 5-4 in the Majors, so she cannot support either. She cannot bid 2NT without a stopper in !Ds. So South bids the fourth suit, 3!D, telling North she knows she must make a bid, but can't find anything appropriate.\nNorth now must find a bid. His choices include rebidding the 5-card !Ss, supporting South's !Cs with a doubleton Queen, or bidding 3NT with the !D K 6 as a stopper. He chooses this last option. It appears that 3NT is the best game for these two hands.
A231: 2over1 | B231: deal10.html | C231: 10 | E231: S:A4 H:KJT8653 D:KQ C:87 | F231: S:9852 H: D:AJT65 C:9532 | G231: S:KJ763 H:AQ7 D:84 C:AQJ | H231: S:QT H:942 D:9732 C:KT64 | I231: South | J231: 1S | pass 2H pass 3H | pass 3S pass 4C | pass 4NT pass 5H | pass 6H all pass | K231: 6H | L231: North | N231: South opens 1!S, her 5-card Major and North responds 2!H. South knows this is a 5-card suit, and bids 3!H, confirming the 8+card trump fit.\nOnce the trump fit is known, North revalues his hand to about 19 points. He makes a slam try with a control-showing bid of 3!S. He knows South won't take this as !S support since the partnership has agreed that !Hs are going to be trumps.\nSouth now shows her control by bidding 4!C.\nThat was what North needed to hear; when Blackwood uncovers two Aces he bids 6!H.\nThe slam is a good one. If either the !SQ or !CK is right there are 12 tricks by way of a finesse. But the best way to play the hand would be to try to establish a !S in the South hand, and if that fails try the !C finesse.
A232: 2over1 | B232: deal11.html | C232: 11 | E232: S:AJT H:AK985 D:K96 C:Q7 | F232: S:K952 H:Q62 D:T873 C:62 | G232: S:863 H:73 D:AQ4 C:AKJT4 | H232: S:Q74 H:JT4 D:J52 C:9853 | I232: West | J232: pass 1H pass 2C | pass 2NT pass 3NT | pass 4NT pass 6NT | pass pass pass | K232: 6NT | L232: North | N232: North opens 1!H and South responds 2!C. Using standard bidding North would now jump to 3NT to show his 19 points, but in 2/1 this is not necessary since the partnership must not stop bidding until game is reached. So North just bids 2NT. South shows her minimum by bidding 3NT.\nNorth will now disclose his extra strength. He bids 4NT. This is not Blackwood, but rather a quantitative raise in Notrump, and an invitation to slam.\nSouth has 15 points, and they are good ones. She accepts the invitation and bids 6NT.\nThere are 11 top tricks. A 3-3 !H split would provide the 12th winner, but this is against the odds. Better to try two !S finesses, a 75% chance.
A233: 2over1 | B233: deal12.html | C233: 12 | E233: S:AJ8752 H:AK D:Q6 C:J87 | F233: S:KT4 H:8764 D:82 C:KT32 | G233: S:Q63 H:Q3 D:AKJ94 C:964 | H233: S:9 H:JT952 D:T753 C:AQ5 | I233: West | J233: pass 1S pass 2D | pass 2S pass 4S | pass pass pass | K233: 4S | L233: North | N233: North opens 1!S and South responds 2!D. North has a pretty good hand, 17 points, but no stopping power in the minor suits. Also, North's !S suit is pretty ragged. Taking these points into consideration, North should just rebid his 6-card suit.\nSouth should now jump to 4!S. This is Fast Arrival, indicating a minimum hand with no particular interest in slam.\nNorth is happy to rest in the game contract.\nEven with a combined 30 points, T tricks are certainly not a sure thing. North must hope that West holds the trump King.
... A259: Bidpractice/Set1 | B259: deal10.html | C259: 10 | E259: S:T962 H:K75 D:954 C:KQ6 | F259: S:753 H:J32 D:AJ72 C:T52 | G259: S:KQJ H:A4 D:KQT8 C:AJ73 | H259: S:A84 H:QT986 D:63 C:984 | I259: South | J259: 2NT | pass 3NT pass pass | pass | K259: 3NT | L259: South | N259: SOUTH has 20 points and 4-4-3-2 distribution, so he opens 2NT.\nNORTH has 8 points. She adds SOUTH's 20 or 21 for a total of 28 or 29, enough for game but\nnowhere close to the slam requirement. So she bids 3NT and SOUTH passes.
A260: Bidpractice/Set1 | B260: deal11.html | C260: 11 | E260: S:KQ4 H:Q95 D:KQ62 C:K83 | F260: S:7532 H:A86 D:984 C:654 | G260: S:AT8 H:KJ3 D:AJ5 C:QJ72 | H260: S:J96 H:T742 D:T73 C:AT9 | I260: West | J260: pass 1NT pass 4NT | pass | K260: 4NT | L260: North
A261: Bidpractice/Set1 | B261: deal12.html | C261: 12 | E261: S:T84 H:Q76 D:KJ3 C:KT52 | F261: S:973 H:A32 D:A982 C:Q63 | G261: S:AQ5 H:K85 D:QT76 C:A97 | H261: S:KJ62 H:JT94 D:54 C:J84 | I261: South | J261: 1NT | pass 2NT pass pass | pass | K261: 2NT | L261: South | N261: SOUTH has a minimum 1NT opening hand - balanced distribution with 15 points.\nNORTH has 9 points, which is not enough to bid game, but is worth making an invitational bid.\nSo she says 2NT.\nSince SOUTH is minimum he declines the invitation by passing.
A262: Bidpractice/Set1 | B262: deal13.html | C262: 13 | E262: S:QJ4 H:AK D:K76 C:QJT52 | F262: S:873 H:J542 D:JT32 C:74 | G262: S:KT5 H:Q63 D:AQ54 C:AK3 | H262: S:A962 H:T987 D:98 C:986 | I262: West | J262: pass 1NT pass 6NT | pass | K262: 6NT | L262: North
A263: Bidpractice/Set1 | B263: deal14.html | C263: 14 | E263: S:K74 H:QJ5 D:KJT C:A743 | F263: S:863 H:T32 D:9872 C:J62 | G263: S:QJ9 H:AK8 D:AQ53 C:KQ8 | H263: S:AT52 H:9764 D:64 C:T95 | I263: South | J263: 2NT | pass 6NT pass pass | pass | K263: 6NT | L263: South | N263: The partner who is first sure what the final contract should be should just go ahead and bid it.\nThis is called "She who knows, goes."\nIn this deal, for example, it is NORTH who knows. She has a balanced 14 points, so when SOUTH indicates\n20/21 points with his opening 2NT bid she\nKNOWS\nthe partnership holds about 34/35 points.\nTherefore she\nGOES\nto 6NT.
A264: Bidpractice/Set1 | B264: deal15.html | C264: 15 | E264: S:AT6 H:AQ4 D:KQJT C:KJ7 | F264: S:J94 H:J32 D:975 C:AQ42 | G264: S:853 H:K96 D:A863 C:965 | H264: S:KQ72 H:T875 D:42 C:T83 | I264: West | J264: pass 2NT pass 3NT | pass pass pass | K264: 3NT | L264: North | N264: NORTH has a balanced 20 point hand - ideal to open 2NT.\nSOUTH has 7 points; he knows the partnership has either 27 or 28 points so he bids 3NT.
A265: Bidpractice/Set1 | B265: deal16.html | C265: 16 | E265: S:764 H:AK8 D:KQ C:AJT74 | F265: S:T93 H:Q2 D:JT763 C:952 | G265: S:AK5 H:T743 D:A982 C:KQ | H265: S:QJ82 H:J965 D:54 C:863 | I265: South | J265: 1NT | pass 6NT pass pass | pass | K265: 6NT | L265: South | N265: This is another example of "She who knows, goes."\nNORTH has a solid 18 points, (1 extra for the fifth Club), so when SOUTH opens 1NT\nshe\nKNOWS\nthat together they must hold at least 33 points. The may even have 35 points.\nIn any case they should be in slam, so NORTH\nGOES\nto 6NT.
A266: Bidpractice/Set1 | B266: deal17.html | C266: 17 | E266: S:KJ9 H:AQ D:KQJ95 C:KT4 | F266: S:874 H:K432 D:T82 C:A62 | G266: S:T63 H:T85 D:A73 C:Q985 | H266: S:AQ52 H:J976 D:64 C:J73 | I266: West | J266: pass 2NT pass 3NT | pass pass pass | K266: 3NT | L266: North | N266: NORTH has 20 points, counting one extra for the fifth Diamond. Just right to open 2NT.\nSOUTH has 6 points, just enough to bid 3NT.\n(20 + 6 = 26) (21 + 6 = 27)
A267: Bidpractice/Set1 | B267: deal18.html | C267: 18 | E267: S:KJ92 H:A98 D:QT8 C:KQJ | F267: S:764 H:J2 D:KJ762 C:A63 | G267: S:QT3 H:KT6 D:A94 C:T752 | H267: S:A85 H:Q7543 D:53 C:984 | I267: South | J267: pass | pass 1NT pass 2NT | pass 3NT pass pass | pass | K267: 3NT | L267: North | N267: After SOUTH passes initially, NORTH opens 1NT.\nWith 9 points, SOUTH has invitational strength, so he says 2NT.\nNORTH has a small problem - SOUTH's bid tells her to bid 3NT with 17 points, but to pass\nwith 15 points. Her problem is that she has 16! Since it looks to her like a "good" 16 points\nshe bids 3NT. If those 10's and 9's had been 4's and 3's she would have passed.
A268: Bidpractice/Set1 | B268: deal19.html | C268: 19 | E268: S:KQ93 H:KQT D:AJ7 C:QT8 | F268: S:864 H:J32 D:Q9832 C:63 | G268: S:A7 H:A84 D:KT6 C:KJ742 | H268: S:JT52 H:9765 D:54 C:A95 | I268: West | J268: pass 1NT pass 4NT | pass 6NT pass pass | pass | K268: 6NT | L268: North | N268: NORTH has a great 1NT hand - 17 points and 4-3-3-3 shape.\nSOUTH has 16 points; he figures it is possible that NORTH can make a slam, but only\nif she has a 17 point opener. So he bids 4NT, expecting NORTH to bid 6NT if she has 17 points\nbut to pass if she has fewer.\nHe figured right - NORTH had 17 points so she bid 6NT.
A269: Bidpractice/Set1 | B269: deal20.html | C269: 20 | E269: S:K8 H:AK5 D:A8 C:QT9632 | F269: S:QJT53 H:JT D:JT963 C:5 | G269: S:A74 H:Q96 D:KQ52 C:KJ8 | H269: S:962 H:87432 D:74 C:A74 | I269: South | J269: 1NT | pass 6NT pass pass | pass | K269: 6NT | L269: South | N269: NORTH definitely does NOT have a balanced hand. She has two doubletons and a\n6-card Club suit.\nBut she DOES have 18 points, (two extra for the fifth and sixth Clubs), and her 18 added to\nSOUTH's minimum of 15 is enough to bid 6NT.\nNotice how easy this will be to play once that Club suit is established.
A270: Bidpractice/Set1 | B270: deal21.html | C270: 21 | E270: S:QJT H:AJ7 D:AK62 C:KQJ | F270: S:764 H:K3 D:QJT9 C:AT63 | G270: S:K83 H:9652 D:743 C:852 | H270: S:A952 H:QT84 D:85 C:974 | I270: West | J270: pass 2NT pass pass | pass | K270: 2NT | L270: North | N270: With 21 points and 4-3-3-3 distribution, NORTH opens 2NT.\nSOUTH has just 3 points; he knows that NORTH cannot have more than 21 so the partnership\ntotal cannot be more than 24. So he just passes 2NT.
A271: Bidpractice/Set1 | B271: deal22.html | C271: 22 | E271: S:K53 H:K53 D:K53 C:K753 | F271: S:T97 H:Q76 D:QJT7 C:Q96 | G271: S:A42 H:A42 D:A642 C:A42 | H271: S:QJ86 H:JT98 D:98 C:JT8 | I271: South | J271: 1NT | pass 3NT pass pass | pass | K271: 3NT | L271: South | N271: This is an easy one to bid.\nSOUTH has a balanced 16 points so he opens 1NT.\nNORTH has a balanced 12 points so she responds 3NT.\nBUT - just look at how this would play. You might only be able to take 8 tricks.\nSometimes correct bidding gets you to unmakeable contracts. But it's only a game.
A272: Bidpractice/Set1 | B272: deal23.html | C272: 23 | E272: S:AJ5 H:QT93 D:KQJ C:AK6 | F272: S:984 H:A2 D:T986 C:T942 | G272: S:K72 H:KJ5 D:A742 C:QJ8 | H272: S:QT63 H:8764 D:53 C:753 | I272: West | J272: pass 2NT pass 6NT | pass pass pass | K272: 6NT | L272: North | N272: Notrump bidding really is easy, you just add your points to partner's points and then\nbid according to that answer.\nHere SOUTH has 14 points. So when NORTH opens 2NT, showing 20 or 21 points SOUTH knows the\ntotal will come to 34 or 35 so he bids 6NT.
A273: Bidpractice/Set1 | B273: deal24.html | C273: 24 | E273: S:AK6 H:K93 D:K743 C:A62 | F273: S:J98 H:J76 D:AJT8 C:JT9 | G273: S:Q75 H:Q84 D:Q62 C:Q753 | H273: S:T432 H:AT52 D:95 C:K84 | I273: South | J273: pass | pass 1NT pass pass | pass | K273: 1NT | L273: North | N273: SOUTH cannot open with only 8 points.\nFurthermore, when NORTH opens 1NT SOUTH knows that the partnership has a 25 points at most so\nhe passes again.
A274: Bidpractice/Set10 | B274: deal01.html | C274: 1 | E274: S:AKJ74 H:87 D:A76 C:Q54 | F274: S:T85 H:K6 D:5432 C:AT73 | G274: S:Q962 H:952 D:K9 C:9862 | H274: S:3 H:AQJT43 D:QJT8 C:KJ | I274: West | J274: 1H 1S pass pass | pass | K274: 1S | L274: North | N274: NORTH has an opening hand, 15 points, and a 5-card ‚ô† suit. Unfortunately WEST beat her to\nthe punch by opening 1\n‚ô•\n.\nBut NORTH should get into the bidding anyway, by Overcalling 1‚ô†. This shows a good ‚ô† suit\nand somewhere between 9 and 16 points.\nSOUTH has 6 points. If NORTH had actually OPENED 1‚ô†, SOUTH would be obligated to bid. But knowing that\nthe Overcall will not be made with more than 16 points, SOUTH just passes.
... A448: Bidpractice/Set6 | B448: deal07.html | C448: 7 | E448: S:AK63 H:AK82 D:KQJ C:KQ | F448: S:QT95 H:T4 D:T986 C:J62 | G448: S:42 H:QJ975 D:A52 C:753 | H448: S:J87 H:63 D:743 C:AT984 | I448: North | J448: 2C pass 2H | pass 4NT pass 5D | pass 6H pass pass | pass | K448: 6H | L448: South | N448: NORTH has a nice 2‚ô£ opening hand.\nWith 8 points, SOUTH can make a positive response so he bids his 5-card\n‚ô•\nsuit.\nNORTH likes\n‚ô•\ns, knows there are at least 33 points, but needs to make\nsure the opponents don't have two Aces so she uses Blackwood.\nWhen SOUTH shows one Ace NORTH bids 6\n‚ô•\n.
A449: Bidpractice/Set6 | B449: deal08.html | C449: 8 | E449: S:AJ983 H:K72 D:6 C:A874 | F449: S:754 H:64 D:QT985 C:J52 | G449: S:KQT2 H:AQJT5 D:AK2 C:K | H449: S:6 H:983 D:J743 C:QT963 | I449: South | J449: 2C | pass 2S pass 3S | pass 4C pass 4D | pass 4NT pass 5S | pass 7S all pass | K449: 7S | L449: North
A450: Bidpractice/Set6 | B450: deal09.html | C450: 9 | E450: S:KQ86 H:AKJ2 D:AKQ C:86 | F450: S:953 H:QT3 D:JT973 C:KJ | G450: S:AJT72 H:987 D:82 C:Q53 | H450: S:4 H:654 D:654 C:AT9742 | I450: North | J450: 2C pass 2S | pass 3S pass 4S | pass pass pass | K450: 4S | L450: South | N450: NORTH has a minimum 2‚ô£ opening.\nSOUTH, with 8 points and a 5-card suit, should make a positive response, 2‚ô†.\nNORTH shows the ‚ô† support first, to set the trump suit, and to give SOUTH an opportunity\nfor a move toward slam if he wants to do so.\nSOUTH would now make a Control-showing bid IF HE HAD A CONTROL. Since he doesn't he just returns\nto 4‚ô† which NORTH passes.
A451: Bidpractice/Set6 | B451: deal10.html | C451: 10 | E451: S:K63 H:Q85 D:K764 C:953 | F451: S:J872 H:J9643 D:J2 C:82 | G451: S:AQ9 H:AK2 D:A83 C:AJ74 | H451: S:T54 H:T7 D:QT95 C:KQT6 | I451: South | J451: 2C | pass 2NT pass 3NT | pass pass pass | K451: 3NT | L451: North | N451: SOUTH, with 22 points and balanced, opens 2‚ô£, expecting to rebid 2NT.\nBut NORTH responds a positive 2NT, showing a balanced hand with 8 or more points.\nSOUTH bids what his hand is worth, 3NT and NORTH passes.
A452: Bidpractice/Set6 | B452: deal11.html | C452: 11 | E452: S:AK9 H:AJ82 D:A6 C:AK93 | F452: S:T8543 H:43 D:KQJ53 C:Q | G452: S:QJ72 H:QT75 D:72 C:854 | H452: S:6 H:K96 D:T984 C:JT762 | I452: North | J452: 2C pass 2D | pass 2NT pass 3C | pass 3H pass 4H | pass pass pass | K452: 4H | L452: North | N452: NORTH opens 2‚ô£ and SOUTH responds 2\n‚ô¶\nshowing fewer than 8 points.\nNORTH bids 2NT with a 23 point balanced hand.\nSOUTH has enough points to bid 3NT, but with two 4-card Major suits bids 3‚ô£ Stayman instead. NORTH\nwon't confuse this as the second negative since that bid isn't used after a 2NT rebid.\nSo NORTH shows her 4-card\n‚ô•\nsuit and SOUTH bids 4\n‚ô•\n.
A453: Bidpractice/Set6 | B453: deal12.html | C453: 12 | E453: S:Q63 H:Q85 D:K764 C:KJ3 | F453: S:T5 H:JT76 D:Q52 C:T982 | G453: S:AK9 H:AK2 D:A83 C:AQ74 | H453: S:J8742 H:943 D:JT9 C:65 | I453: South | J453: 2C | pass 2NT pass 3NT | pass 6NT pass pass | pass | K453: 6NT | L453: North | N453: NORTH has a balanced hand with 11 points, so she responds 2NT to SOUTH's 2‚ô£ opening bid.\nSOUTH bids 3NT. This shows 22-24 points, a hand he was planning to rebid 2NT.\nNORTH knows the side has at least 33 points, but no more than 35 so she bids 6NT.
A454: Bidpractice/Set6 | B454: deal13.html | C454: 13 | E454: S:AKQ86 H:AKT82 D:A C:86 | F454: S:JT543 H:4 D:KJT93 C:KJ | G454: S:72 H:9753 D:Q742 C:Q93 | H454: S:9 H:QJ6 D:865 C:AT7542 | I454: North | J454: 2C pass 2D | pass 2S pass 2NT | pass 3H pass 4H | pass pass pass | K454: 4H | L454: North | N454: NORTH has both Majors and enough points to open 2‚ô£.\nSOUTH, with 4 points, responds with a negative 2\n‚ô¶\n.\nNORTH first bids her higher ranking suit, 2‚ô†.\nSOUTH is too strong for second negative, he bids 2NT.\nNORTH now shows her second suit, 3\n‚ô•\n.\nSOUTH is happy to bid the game in\n‚ô•\ns.
A455: Bidpractice/Set6 | B455: deal14.html | C455: 14 | E455: S:K73 H:982 D:AQJ86 C:J2 | F455: S:J984 H:J743 D:T4 C:953 | G455: S:AQ2 H:AKQ5 D:K75 C:KQT | H455: S:T65 H:T6 D:932 C:A8764 | I455: South | J455: 2C | pass 3D pass 3NT | pass 6NT pass pass | pass | K455: 6NT | L455: South | N455: SOUTH has a balanced hand with 23 points. He opens 2‚ô£ and expects to rebid 2NT.\nNORTH has 12 points so makes a positive response in her best suit. Since that suit is\n‚ô¶\ns she must jump to the 3-level.\nSOUTH now describes his balanced, minimum hand by bidding 3NT.\nNORTH bids 6NT, knowing that the partnership holds at least 34 points.
A456: Bidpractice/Set6 | B456: deal15.html | C456: 15 | E456: S:K6 H:AKQJ2 D:KQJ C:KQJ | F456: S:QJ3 H:T8 D:63 C:T87652 | G456: S:AT972 H:975 D:852 C:A3 | H456: S:854 H:643 D:AT974 C:94 | I456: North | J456: 2C pass 2S | pass 3H pass 4H | pass 4NT pass 5H | pass 6H pass pass | pass pass pass | K456: 6H | L456: North | N456: pass\npass\nSOUTH, with 9 points and a 5-card suit, should make a positive response, 2‚ô†.\nNORTH bids her\n‚ô•\ns and SOUTH agrees the trump suit with a\n4\n‚ô•\nbid.\nNORTH thinks there is a slam, so she invokes Blackwood. Hearing that SOUTH holds two Aces she bids\n6NT. She could also have bid 6\n‚ô•\nbut 6NT scores a little more.
A457: Bidpractice/Set6 | B457: deal16.html | C457: 16 | E457: S:J42 H:8752 D:J72 C:K63 | F457: S:7 H:943 D:AQ54 C:T8752 | G457: S:AKQT3 H:AK6 D:86 C:AQ4 | H457: S:9865 H:QJT D:KT93 C:J9 | I457: South | J457: 2C | pass 2D pass 2S | pass 3S pass 4S | pass pass pass | K457: 4S | L457: South | N457: NORTH has 5 points, so she responds 2\n‚ô¶\nto SOUTH's opening 2‚ô£ bid.\nSOUTH bids his 5-card ‚ô† suit.\nNORTH is too good for the second negative, so she supports SOUTH's ‚ô†.\nSOUTH doesn't have enough to think about slam, so he signs off at 4‚ô†.
A458: Bidpractice/Set6 | B458: deal17.html | C458: 17 | E458: S:AQ H:KQJ2 D:AQ98 C:AK4 | F458: S:T984 H:8 D:T73 C:QT982 | G458: S:KJ72 H:A75 D:J42 C:653 | H458: S:653 H:T9643 D:K65 C:J7 | I458: North | J458: 2C pass 2NT | pass 6NT pass pass | pass | K458: 6NT | L458: South | N458: NORTH opens 2‚ô£ with her balanced 25 points.\nSOUTH has 9 points but no 5-card suit. He should make a positive response of 2NT.\nNORTH figures SOUTH for 8 points and bids 6NT. If SOUTH has significantly more than\n8 it will be up to him to go to 7NT. But he doesn't.
A459: Bidpractice/Set6 | B459: deal18.html | C459: 18 | E459: S:7 H:KQJ832 D:986 C:874 | F459: S:AT94 H:7 D:T73 C:QT963 | G459: S:KQJ82 H:A5 D:AK2 C:AK2 | H459: S:653 H:T964 D:QJ54 C:J5 | I459: South | J459: 2C | pass 2H pass 2S | pass 3H pass 6H | pass pass all pass | K459: 6H | L459: North
A460: Bidpractice/Set6 | B460: deal19.html | C460: 19 | E460: S:KQ87 H:AKQ2 D:AKJ6 C:6 | F460: S:632 H:JT43 D:T43 C:T92 | G460: S:AJT5 H:85 D:Q72 C:KQ53 | H460: S:94 H:976 D:985 C:AJ874 | I460: North | J460: 2C pass 2NT | pass 3C pass 3S | pass 4S pass 6S | pass pass pass | K460: 6S | L460: South | N460: After NORTH's 2‚ô£ opening, SOUTH bids 2NT, showing a balanced hand of at least 8 points. SOUTH\nactually has 12 points, but the time to show the extra strength will be later.\nNORTH's 3‚ô£ bid is Stayman, asking SOUTH for a 4-card Major. SOUTH mentions his ‚ô†s and\nNORTH bids 4‚ô†, showing a minimum 2‚ô£ opener with 4 ‚ô†s.\nNow SOUTH adds his 12 points to NORTH's 22 minimum and gets 34. He bids 6‚ô†.
A461: Bidpractice/Set6 | B461: deal20.html | C461: 20 | E461: S:2 H:QJ52 D:9872 C:T763 | F461: S:JT95 H:4 D:J5 C:KQ9852 | G461: S:AKQ63 H:AKT96 D:T6 C:A | H461: S:874 H:873 D:AKQ43 C:J4 | I461: South | J461: 2C | pass 2D pass 2S | pass 3C pass 3H | pass 4H pass pass | pass | K461: 4H | L461: South | N461: NORTH has 3 points, so she responds 2\n‚ô¶\nto SOUTH's opening 2‚ô£ bid,\nthen bids 3‚ô£ as a second-negative when SOUTH bids 2‚ô†.\nHowever, when SOUTH then bids\n‚ô•\ns, NORTH finds two more points\nand bids 4\n‚ô•\n.
A462: Bidpractice/Set6 | B462: deal21.html | C462: 21 | E462: S:QT85 H:AK6 D:AK8 C:KQJ | F462: S:A76 H:J92 D:964 C:9842 | G462: S:KJ2 H:Q75 D:QT72 C:753 | H462: S:943 H:T843 D:J53 C:AT6 | I462: North | J462: 2C pass 2NT | pass 3NT pass pass | pass | K462: 3NT | L462: South | N462: NORTH expected to open 2‚ô£, then bid 2NT at her second turn.\nBut SOUTH, with 8 points and a balanced hand, responds 2NT, so NORTH must adapt. She shows\nher minimum, balanced, 22-point hand by bidding 3NT.\nSince NORTH has just the 8 points minimum that he promised, he passes 3NT.
A463: Bidpractice/Set6 | B463: deal22.html | C463: 22 | E463: S:K987 H:QJ82 D:986 C:74 | F463: S:5 H:643 D:AT2 C:KT8532 | G463: S:AQJ2 H:AK5 D:KQ73 C:A6 | H463: S:T643 H:T97 D:J54 C:QJ9 | I463: South | J463: 2C | pass 2D pass 2NT | pass 3C pass 3S | pass 4S all pass | K463: 4S | L463: South
A464: Bidpractice/Set6 | B464: deal23.html | C464: 23 | E464: S:A8 H:KQ4 D:AKQJ86 C:K4 | F464: S:Q954 H:T6 D:53 C:QJ976 | G464: S:K72 H:A975 D:T72 C:A53 | H464: S:JT63 H:J832 D:94 C:T82 | I464: North | J464: 2C pass 2NT | pass 4C pass 4S | pass 5C pass 5H | pass 7NT all pass | K464: 7NT | L464: South
A465: Bidpractice/Set6 | B465: deal24.html | C465: 24 | E465: S:973 H:62 D:QJ9863 C:A4 | F465: S:AQJ52 H:843 D:5 C:8752 | G465: S:8 H:AKQ5 D:AK72 C:KQJ3 | H465: S:KT64 H:JT97 D:T4 C:T96 | I465: South | J465: 2C | pass 3D pass 4NT | pass 5D pass 6D | pass pass pass | K465: 6D | L465: North | N465: When SOUTH opens 2‚ô£ NORTH has enough strength (9 points) for a positive response. But,\nbecause her suit is\n‚ô¶\ns, she must jump to 3\n‚ô¶\n.\nSOUTH thinks slam and uses Blackwood to discover that NORTH holds one Ace.\nThat's all NORTH needs to know to bid 6\n‚ô¶\n.
A466: Bidpractice/Set7 | B466: deal01.html | C466: 1 | E466: S:AKQ983 H:2 D:AK C:KQJ8 | F466: S:T5 H:A97 D:J975 C:T942 | G466: S:J742 H:KQ54 D:82 C:753 | H466: S:6 H:JT863 D:QT643 C:A6 | I466: North | J466: 2C pass 2D | pass 2S pass 3S | pass 4NT pass 5C | pass 5S pass pass | pass | K466: 5S | L466: North | N466: SOUTH's 3‚ô† supporting bid is enough to convince NORTH to make a slam try.\nNORTH bids Blackwood 4NT. If SOUTH shows one Ace NORTH plans to bid 6‚ô†, but\nwhen SOUTH bids 5‚ô£ NORTH settles for 5‚ô†
A467: Bidpractice/Set7 | B467: deal02.html | C467: 2 | E467: S:J3 H:AQT86 D:T3 C:JT74 | F467: S:KT95 H:72 D:764 C:8632 | G467: S:A64 H:KJ9 D:AKQJ9 C:KQ | H467: S:Q872 H:543 D:852 C:A95 | I467: South | J467: 2C | pass 2H pass 4NT | pass 5D pass 6H | pass pass pass | K467: 6H | L467: North | N467: NORTH makes a positive 3\n‚ô•\nresponse to SOUTH's 2‚ô£ opener.\nThis promises at least 8 points and a 5-card suit with two or more honors.\nSOUTH only needs to know one thing - how many Aces in the NORTH hand.\nA Blackwood 4NT tells her the answer is one, so she bids 6\n‚ô•\n.
...
